Workbook

Sheet Raw Data
B1: AIB GROUP — RAW HISTORICAL DATA (2019–2025) | Source: AIB Annual Reports + Pillar 3 Q4 2025
B4: A. LOAN BOOK COMPOSITION (€ Millions, Gross)
B5: Segment | C5: 2020 | D5: =C5+1 -> 2021 | E5: =D5+1 -> 2022 | F5: =E5+1 -> 2023 | G5: =F5+1 -> 2024 | H5: =G5+1 -> 2025 | I5: Source
B6: Residential Mortgages | C6: ='2020'!D12 -> 31486 | D6: ='2021'!D12 -> 30652 | E6: ='2022'!D17 -> 31447 | F6: ='2023'!D18 -> 36000 | G6: ='2024'!D18 -> 38547 | H6: ='2025'!D19 -> 38940
B7: Other Personal | C7: ='2020'!D13 -> 5635 | D7: ='2021'!D13 -> 5560 | E7: ='2022'!D18 -> 5589 | F7: ='2023'!D19 -> 5866 | G7: ='2024'!D19 -> 6251 | H7: ='2025'!D20 -> 6481
B8: Property & Construction | C8: ='2020'!D11 -> 9200 | D8: ='2021'!D11 -> 9725 | E8: ='2022'!D16 -> 11001 | F8: ='2023'!D17 -> 11461 | G8: ='2024'!D17 -> 10864 | H8: ='2025'!D18 -> 10494
B9: Non-Property Business(SME) | C9: ='2020'!O13 -> 18211 | D9: ='2021'!P13 -> 18145 | E9: ='2022'!O16 -> 13939 | F9: ='2023'!O17 -> 14674 | G9: ='2024'!O17 -> 15727 | H9: ='2025'!N17 -> 16201
B10: Non-Property Business(Corporate other) | C10: ='2020'!O7 -> 7970 | D10: ='2021'!P7 -> 8614 | E10: ='2022'!O9 -> 14868 | F10: ='2023'!O10 -> 15961 | G10: ='2024'!O10 -> 17579 | H10: ='2025'!N11 -> 18382
B11: TOTAL GROSS LOANS | C11: =SUM(C6:C10) -> 72502 | D11: =SUM(D6:D10) -> 72696 | E11: =SUM(E6:E10) -> 76844 | F11: =SUM(F6:F10) -> 83962 | G11: =SUM(G6:G10) -> 88968 | H11: =SUM(H6:H10) -> 90498
B14: B. Non-Performing Loan : Stage 3+ POCI (€ Millions)
B15: Segment | C15: 2020 | D15: =C15+1 -> 2021 | E15: =D15+1 -> 2022 | F15: =E15+1 -> 2023 | G15: =F15+1 -> 2024 | H15: =G15+1 -> 2025 | I15: Source
B16: Residential Mortgages | C16: ='2020'!G12+'2020'!H12 -> 2176 | D16: ='2021'!G12+'2021'!H12 -> 1033 | E16: ='2022'!G17+'2022'!H17 -> 733 | F16: ='2023'!G18+'2023'!H18 -> 793 | G16: ='2024'!G18+'2024'!H18 -> 946 | H16: ='2025'!G19+'2025'!H19 -> 746
B17: Other Personal | C17: ='2020'!G13+'2020'!H13 -> 242 | D17: ='2021'!G13+'2021'!H13 -> 258 | E17: ='2022'!G18+'2022'!H18 -> 188 | F17: ='2023'!G19+'2023'!H19 -> 90 | G17: ='2024'!G19+'2024'!H19 -> 109 | H17: ='2025'!G20+'2025'!H20 -> 96
B18: Property & Construction | C18: ='2020'!G11+'2020'!H11 -> 902 | D18: ='2021'!G11+'2021'!H11 -> 671 | E18: ='2022'!G16+'2022'!H16 -> 436 | F18: ='2023'!G17+'2023'!H17 -> 687 | G18: ='2024'!G17+'2024'!H17 -> 577 | H18: ='2025'!G18+'2025'!H18 -> 375
B19: Non-Property Business(SME) | C19: ='2020'!R13+'2020'!S13 -> 970 | D19: ='2021'!S13+'2021'!T13 -> 1079 | E19: ='2022'!R16+'2022'!S16 -> 621 | F19: ='2023'!R17+'2023'!S17 -> 440 | G19: ='2024'!R17+'2024'!S17 -> 406 | H19: ='2025'!Q17+'2025'!R17 -> 267
B20: Non-Property Business(Corporate other) | C20: ='2020'!R7+'2020'!S7 -> 132 | D20: ='2021'!S7+'2021'!T7 -> 108 | E20: ='2022'!R9+'2022'!S9 -> 205 | F20: ='2023'!R10+'2023'!S10 -> 129 | G20: ='2024'!R10+'2024'!S10 -> 142 | H20: ='2025'!Q11+'2025'!R11 -> 344
B21: TOTAL GROSS LOANS | C21: =SUM(C16:C20) -> 4422 | D21: =SUM(D16:D20) -> 3149 | E21: =SUM(E16:E20) -> 2183 | F21: =SUM(F16:F20) -> 2139 | G21: =SUM(G16:G20) -> 2180 | H21: =SUM(H16:H20) -> 1828
B24: C. NPL RATIOS BY SEGMENT (NPL / Total Loans)
B25: Segment | C25: 2020 | D25: =C25+1 -> 2021 | E25: =D25+1 -> 2022 | F25: =E25+1 -> 2023 | G25: =F25+1 -> 2024 | H25: =G25+1 -> 2025 | I25: Source
B26: Residential Mortgages | C26: =C16/C6 -> 0.069110081 | D26: =D16/D6 -> 0.0337009 | E26: =E16/E6 -> 0.02330906 | F26: =F16/F6 -> 0.022027778 | G26: =G16/G6 -> 0.024541469 | H26: =H16/H6 -> 0.019157678
B27: Other Personal | C27: =C17/C7 -> 0.042945874 | D27: =D17/D7 -> 0.046402878 | E27: =E17/E7 -> 0.033637502 | F27: =F17/F7 -> 0.015342653 | G27: =G17/G7 -> 0.01743721 | H27: =H17/H7 -> 0.014812529
B28: Property & Construction | C28: =C18/C8 -> 0.098043478 | D28: =D18/D8 -> 0.068997429 | E28: =E18/E8 -> 0.039632761 | F28: =F18/F8 -> 0.059942413 | G28: =G18/G8 -> 0.053111193 | H28: =H18/H8 -> 0.035734706
B29: Non-Property Business(SME) | C29: =C19/C9 -> 0.05326451 | D29: =D19/D9 -> 0.059465417 | E29: =E19/E9 -> 0.044551259 | F29: =F19/F9 -> 0.029985007 | G29: =G19/G9 -> 0.025815477 | H29: =H19/H9 -> 0.016480464
B30: Non-Property Business(Corporate other) | C30: =C20/C10 -> 0.016562108 | D30: =D20/D10 -> 0.012537729 | E30: =E20/E10 -> 0.013788001 | F30: =F20/F10 -> 0.0080822004 | G30: =G20/G10 -> 0.0080778201 | H30: =H20/H10 -> 0.018713959
B31: GROUP NPL RATIO | C31: =C21/C11 -> 0.060991421 | D31: =D21/D11 -> 0.043317376 | E31: =E21/E11 -> 0.028408204 | F31: =F21/F11 -> 0.02547581 | G31: =G21/G11 -> 0.024503192 | H31: =H21/H11 -> 0.020199341
B34: D. Expected Credit Loss allowance By Segment : Stage 3+ POCI (€ Millions)
B35: Segment | C35: 2020 | D35: =C35+1 -> 2021 | E35: =D35+1 -> 2022 | F35: =E35+1 -> 2023 | G35: =F35+1 -> 2024 | H35: =G35+1 -> 2025 | I35: Source
B36: Residential Mortgages | C36: ='2020'!G28+'2020'!H28 -> 731 | D36: ='2021'!G27+'2021'!H27 -> 306 | E36: ='2022'!G38+'2022'!H38 -> 206 | F36: ='2023'!G38+'2023'!H38 -> 214 | G36: ='2024'!G39+'2024'!H39 -> 207 | H36: ='2025'!G39+'2025'!H39 -> 115
B37: Other Personal | C37: ='2020'!G29+'2020'!H29 -> 143 | D37: ='2021'!G28+'2021'!H28 -> 159 | E37: ='2022'!G39+'2022'!H39 -> 116 | F37: ='2023'!G39+'2023'!H39 -> 45 | G37: ='2024'!G40+'2024'!H40 -> 66 | H37: ='2025'!G40+'2025'!H40 -> 62
B38: Property & Construction | C38: ='2020'!G27+'2020'!H27 -> 204 | D38: ='2021'!G26+'2021'!H26 -> 187 | E38: ='2022'!G37+'2022'!H37 -> 132 | F38: ='2023'!G37+'2023'!H37 -> 204 | G38: ='2024'!G38+'2024'!H38 -> 187 | H38: ='2025'!G38+'2025'!H38 -> 145
B39: Non-Property Business(SME) | C39: ='2020'!R29+'2020'!S29 -> 294 | D39: ='2021'!S28+'2021'!T28 -> 297 | E39: ='2022'!R37+'2022'!S37 -> 191 | F39: ='2023'!R37+'2023'!S37 -> 124 | G39: ='2024'!R38+'2024'!S38 -> 143 | H39: ='2025'!Q39+'2025'!R39 -> 77
B40: Non-Property Business(Corporate other) | C40: ='2020'!R23+'2020'!S23 -> 33 | D40: ='2021'!S22+'2021'!T22 -> 22 | E40: ='2022'!R30+'2022'!S30 -> 82 | F40: ='2023'!R30+'2023'!S30 -> 58 | G40: ='2024'!R31+'2024'!S31 -> 46 | H40: ='2025'!Q32+'2025'!R32 -> 84
B41: GROUP NPL RATIO | C41: =SUM(C36:C40) -> 1405 | D41: =SUM(D36:D40) -> 971 | E41: =SUM(E36:E40) -> 727 | F41: =SUM(F36:F40) -> 645 | G41: =SUM(G36:G40) -> 649 | H41: =SUM(H36:H40) -> 483
B44: E. PROVISION COVERAGE RATIOS (ECL Provisions / NPL Balance)
B45: Segment | C45: 2020 | D45: =C45+1 -> 2021 | E45: =D45+1 -> 2022 | F45: =E45+1 -> 2023 | G45: =F45+1 -> 2024 | H45: =G45+1 -> 2025 | I45: Source
B46: Residential Mortgages | C46: =C36/C16 -> 0.3359375 | D46: =D36/D16 -> 0.29622459 | E46: =E36/E16 -> 0.28103683 | F46: =F36/F16 -> 0.26986129 | G46: =G36/G16 -> 0.21881607 | H46: =H36/H16 -> 0.1541555
B47: Other Personal | C47: =C37/C17 -> 0.59090909 | D47: =D37/D17 -> 0.61627907 | E47: =E37/E17 -> 0.61702128 | F47: =F37/F17 -> 0.5 | G47: =G37/G17 -> 0.60550459 | H47: =H37/H17 -> 0.64583333
B48: Property & Construction | C48: =C38/C18 -> 0.22616408 | D48: =D38/D18 -> 0.27868852 | E48: =E38/E18 -> 0.30275229 | F48: =F38/F18 -> 0.29694323 | G48: =G38/G18 -> 0.32409012 | H48: =H38/H18 -> 0.38666667
B49: Non-Property Business(SME) | C49: =C39/C19 -> 0.30309278 | D49: =D39/D19 -> 0.27525487 | E49: =E39/E19 -> 0.30756844 | F49: =F39/F19 -> 0.28181818 | G49: =G39/G19 -> 0.35221675 | H49: =H39/H19 -> 0.28838951
B50: Non-Property Business(Corporate other) | C50: =C40/C20 -> 0.25 | D50: =D40/D20 -> 0.2037037 | E50: =E40/E20 -> 0.4 | F50: =F40/F20 -> 0.4496124 | G50: =G40/G20 -> 0.32394366 | H50: =H40/H20 -> 0.24418605
B51: GROUP NPL RATIO | C51: =C41/C21 -> 0.31772953 | D51: =D41/D21 -> 0.30835186 | E51: =E41/E21 -> 0.33302794 | F51: =F41/F21 -> 0.30154278 | G51: =G41/G21 -> 0.29770642 | H51: =H41/H21 -> 0.26422319
B54: D. COST OF RISK (Impairment Charge / Average Loans — basis points)
B55: Metric | C55: 2020 | D55: 2021 | E55: 2022 | F55: 2023 | G55: 2024 | H55: 2025 | I55: Source
B56: Impairment Charge (€m) | C56: -1460 | D56: 238 | E56: 7 | F56: 172 | G56: 55 | H56: 172 | I56: 2025: est from trend; impairment continuing to normalise
B57: Average Gross Loans (€m) | C57: =AVERAGE(C11,D11) -> 72599 | D57: =AVERAGE(D11,E11) -> 74770 | E57: =AVERAGE(E11,F11) -> 80403 | F57: =AVERAGE(F11,G11) -> 86465 | G57: =AVERAGE(G11,H11) -> 89733 | H57: =AVERAGE(H11,I11) -> 90498 | I57: 2025: est from trend; impairment continuing to normalise
B58: Cost of Risk (bps) | C58: =C56/C57*10000 -> -201.1047 | D58: =D56/D57*10000 -> 31.830948 | E58: =E56/E57*10000 -> 0.87061428 | F58: =F56/F57*10000 -> 19.892442 | G58: =G56/G57*10000 -> 6.1292947 | H58: =H56/H57*10000 -> 19.005945 | I58: 2025: est from trend; impairment continuing to normalise
B61: E. IFRS 9 STAGE BALANCES (€m)
B62: Stage / Metric | C62: 2020 | D62: =C62+1 -> 2021 | E62: =D62+1 -> 2022 | F62: =E62+1 -> 2023 | G62: =F62+1 -> 2024 | H62: =G62+1 -> 2025 | I62: Note
B63: Stage 1 — Performing (€m) | C63: 57412 | D63: 61961 | E63: 67547 | F63: 72963 | G63: 77356 | H63: ='2025'!E21 -> 79466 | I63: 12m ECL; 2025 est from gross loans - S2 - S3
B64: Stage 2 — Sig. Credit Risk (€m) | C64: 10668 | D64: 7586 | E64: 7114 | F64: 8860 | G64: 9432 | H64: ='2025'!F21 -> 9204 | I64: ⚠ Lifetime ECL — early warning; 2025 est improving trend
B65: Stage 3 — Credit Impaired (€m) | C65: 4238 | D65: 3046 | E65: 2096 | F65: 2008 | G65: 1986 | H65: ='2025'!G21 -> 1662 | I65: 2025 = 1,596 CONFIRMED Pillar 3 CR2
B66: Stage 1 ECL Provision (€m) | C66: 304 | D66: 257 | E66: 284 | F66: 268 | G66: 201 | H66: ='2025'!E41 -> 186 | I66: 12-month ECL provision
B67: Stage 2 ECL Provision (€m) | C67: 884 | D67: 736 | E67: 685 | F67: 666 | G67: 551 | H67: ='2025'!F41 -> 522 | I67: Lifetime ECL provision
B68: Stage 3 ECL Provision (€m) | C68: 1336 | D68: 940 | E68: 718 | F68: 647 | G68: 660 | H68: ='2025'!G41 -> 499 | I68: 2025: total impairment 1,149; Stage3 est 724

Sheet EL Loss model
B1: EXPECTED LOSS MODEL (EL = PD × LGD × EAD) | 2019–2025 | € Millions
B4: PART 1 — PD INPUTS | N4: NPL ratios are used as a proxy for PD due to the absence of segment-level disclosed PD data.
B5: Segment | C5: 2020 | D5: =C5+1 -> 2021 | E5: =D5+1 -> 2022 | F5: =E5+1 -> 2023 | G5: =F5+1 -> 2024 | H5: =G5+1 -> 2025 | I5: Source
B6: Residential Mortgages | C6: ='Raw Data'!C26 -> 0.069110081 | D6: 0.0374 | E6: 0.024 | F6: 0.0231 | G6: 0.0211 | H6: 0.0165 | I6: AIB Pillar 3 disclosures
B7: Other Personal | C7: ='Raw Data'!C27 -> 0.042945874 | D7: ='Raw Data'!D27 -> 0.046402878 | E7: ='Raw Data'!E27 -> 0.033637502 | F7: ='Raw Data'!F27 -> 0.015342653 | G7: ='Raw Data'!G27 -> 0.01743721 | H7: ='Raw Data'!H27 -> 0.014812529 | I7: Proxy From NPL Ratios
B8: Property & Construction | C8: ='Raw Data'!C28 -> 0.098043478 | D8: ='Raw Data'!D28 -> 0.068997429 | E8: ='Raw Data'!E28 -> 0.039632761 | F8: ='Raw Data'!F28 -> 0.059942413 | G8: ='Raw Data'!G28 -> 0.053111193 | H8: ='Raw Data'!H28 -> 0.035734706 | I8: AIB Pillar 3 disclosures
B9: Non-Property Business(SME) | C9: ='Raw Data'!C29 -> 0.05326451 | D9: ='Raw Data'!D29 -> 0.059465417 | E9: ='Raw Data'!E29 -> 0.044551259 | F9: ='Raw Data'!F29 -> 0.029985007 | G9: ='Raw Data'!G29 -> 0.025815477 | H9: ='Raw Data'!H29 -> 0.016480464 | I9: AIB Pillar 3 disclosures(SME PD sourced from AIB Pillar 3 CR6 table (Corporates - SME without own estimates). Weighted average PD includes defaulted exposures and regulatory conservatism margins, resulting in higher figures than the observed NPL ratio. This is appropriate for a regulatory EL framework.)
B10: Non-Property Business(Corporate other) | C10: ='Raw Data'!C30 -> 0.016562108 | D10: 0.0197 | E10: 0.0178 | F10: 0.0125 | G10: 0.0173 | H10: 0.0418 | I10: AIB Pillar 3 disclosures
B13: PART 2 — LGD INPUTS
B14: Segment | C14: 2020 | D14: =C14+1 -> 2021 | E14: =D14+1 -> 2022 | F14: =E14+1 -> 2023 | G14: =F14+1 -> 2024 | H14: =G14+1 -> 2025 | I14: Source
B15: Residential Mortgages | C15: 0.285 | D15: 0.285 | E15: 0.2855 | F15: 0.2882 | G15: 0.3325 | H15: 0.3298 | I15: AIB Pillar 3 disclosures
B16: Other Personal | C16: ='Raw Data'!C47 -> 0.59090909 | D16: ='Raw Data'!D47 -> 0.61627907 | E16: ='Raw Data'!E47 -> 0.61702128 | F16: ='Raw Data'!F47 -> 0.5 | G16: ='Raw Data'!G47 -> 0.60550459 | H16: ='Raw Data'!H47 -> 0.64583333 | I16: Proxy Coverage ratio
B17: Property & Construction | C17: 0.4652 | D17: 0.4652 | E17: 0.4706 | F17: 0.4917 | G17: 0.4819 | H17: 0.4276 | I17: AIB Pillar 3 disclosures
B18: Non-Property Business(SME) | C18: 0.4497 | D18: 0.4497 | E18: 0.4474 | F18: 0.4476 | G18: 0.4479 | H18: 0.4479 | I18: AIB Pillar 3 disclosures
B19: Non-Property Business(Corporate other) | C19: 0.4448 | D19: 0.4448 | E19: 0.4445 | F19: 0.4425 | G19: 0.4528 | H19: 0.394 | I19: AIB Pillar 3 disclosures
B22: PART 3 — EAD INPUTS (Exposure at Default = Gross Loan Balance, linked from Raw Data)
B23: Segment | C23: 2020 | D23: =C23+1 -> 2021 | E23: =D23+1 -> 2022 | F23: =E23+1 -> 2023 | G23: =F23+1 -> 2024 | H23: =G23+1 -> 2025 | I23: Source
B24: Residential Mortgages | C24: ='Raw Data'!C6 -> 31486 | D24: ='Raw Data'!D6 -> 30652 | E24: ='Raw Data'!E6 -> 31447 | F24: ='Raw Data'!F6 -> 36000 | G24: ='Raw Data'!G6 -> 38547 | H24: ='Raw Data'!H6 -> 38940
B25: Other Personal | C25: ='Raw Data'!C7 -> 5635 | D25: ='Raw Data'!D7 -> 5560 | E25: ='Raw Data'!E7 -> 5589 | F25: ='Raw Data'!F7 -> 5866 | G25: ='Raw Data'!G7 -> 6251 | H25: ='Raw Data'!H7 -> 6481
B26: Property & Construction | C26: ='Raw Data'!C8 -> 9200 | D26: ='Raw Data'!D8 -> 9725 | E26: ='Raw Data'!E8 -> 11001 | F26: ='Raw Data'!F8 -> 11461 | G26: ='Raw Data'!G8 -> 10864 | H26: ='Raw Data'!H8 -> 10494
B27: Non-Property Business(SME) | C27: ='Raw Data'!C9 -> 18211 | D27: ='Raw Data'!D9 -> 18145 | E27: ='Raw Data'!E9 -> 13939 | F27: ='Raw Data'!F9 -> 14674 | G27: ='Raw Data'!G9 -> 15727 | H27: ='Raw Data'!H9 -> 16201
B28: Non-Property Business(Corporate other) | C28: ='Raw Data'!C10 -> 7970 | D28: ='Raw Data'!D10 -> 8614 | E28: ='Raw Data'!E10 -> 14868 | F28: ='Raw Data'!F10 -> 15961 | G28: ='Raw Data'!G10 -> 17579 | H28: ='Raw Data'!H10 -> 18382
B31: EXPECTED LOSS (EL = PD × LGD × EAD) €m
B32: Segment | C32: 2020 | D32: =C32+1 -> 2021 | E32: =D32+1 -> 2022 | F32: =E32+1 -> 2023 | G32: =F32+1 -> 2024 | H32: =G32+1 -> 2025 | I32: Δ 2019→2025 | J32: EL % EAD (2025)
B33: Residential Mortgages | C33: =(C6*C15*C24) -> 620.16 | D33: =(D6*D15*D24) -> 326.71967 | E33: =(E6*E15*E24) -> 215.47484 | F33: =(F6*F15*F24) -> 239.66712 | G33: =(G6*G15*G24) -> 270.43612 | H33: =(H6*H15*H24) -> 211.8998 | I33: =H33-C33 -> -408.2602 | J33: =H33/C24 -> 0.0067299688
B34: Other Personal | C34: =(C7*C16*C25) -> 143 | D34: =(D7*D16*D25) -> 159 | E34: =(E7*E16*E25) -> 116 | F34: =(F7*F16*F25) -> 45 | G34: =(G7*G16*G25) -> 66 | H34: =(H7*H16*H25) -> 62 | I34: =H34-C34 -> -81 | J34: =H34/C25 -> 0.011002662
B35: Property & Construction | C35: =(C8*C17*C26) -> 419.6104 | D35: =(D8*D17*D26) -> 312.1492 | E35: =(E8*E17*E26) -> 205.1816 | F35: =(F8*F17*F26) -> 337.7979 | G35: =(G8*G17*G26) -> 278.0563 | H35: =(H8*H17*H26) -> 160.35 | I35: =H35-C35 -> -259.2604 | J35: =H35/C26 -> 0.017429348
B36: Non-Property Business(SME) | C36: =(C9*C18*C27) -> 436.209 | D36: =(D9*D18*D27) -> 485.2263 | E36: =(E9*E18*E27) -> 277.8354 | F36: =(F9*F18*F27) -> 196.944 | G36: =(G9*G18*G27) -> 181.8474 | H36: =(H9*H18*H27) -> 119.5893 | I36: =H36-C36 -> -316.6197 | J36: =H36/C27 -> 0.0065668717
B37: Non-Property Business(Corporate other) | C37: =(C10*C19*C28) -> 58.7136 | D37: =(D10*D19*D28) -> 75.480692 | E37: =(E10*E19*E28) -> 117.6371 | F37: =(F10*F19*F28) -> 88.284281 | G37: =(G10*G19*G28) -> 137.70404 | H37: =(H10*H19*H28) -> 302.73683 | I37: =H37-C37 -> 244.02323 | J37: =H37/C28 -> 0.037984546
B38: TOTAL EXPECTED LOSS (€m) | C38: =SUM(C33:C37) -> 1677.693 | D38: =SUM(D33:D37) -> 1358.5759 | E38: =SUM(E33:E37) -> 932.12895 | F38: =SUM(F33:F37) -> 907.6933 | G38: =SUM(G33:G37) -> 934.04386 | H38: =SUM(H33:H37) -> 856.57593
B40: PART 4 — PROVISION vs MODEL EL (Coverage Gap)
B41: Metric | C41: 2020 | D41: =C41+1 -> 2021 | E41: =D41+1 -> 2022 | F41: =E41+1 -> 2023 | G41: =F41+1 -> 2024 | H41: =G41+1 -> 2025 | I41: Source | K41: 2025 | L41: Formula / basis | M41: Meaning | N41: Illustrative value (€m)
B42: Actual ECL Provisions (€m) | C42: ='2020'!D30 -> 2593 | D42: ='2021'!D29 -> 1964 | E42: ='2022'!D40 -> 1696 | F42: ='2023'!D40 -> 1579 | G42: ='2024'!D41 -> 1401 | H42: ='2025'!D41 -> 1191 | K42: Base model EL | L42: PD × LGD × EAD | M42: model | N42: 856.576
B43: Model EL (€m) | C43: =C38 -> 1677.693 | D43: =D38 -> 1358.5759 | E43: =E38 -> 932.12895 | F43: =F38 -> 907.6933 | G43: =G38 -> 934.04386 | H43: =H38 -> 856.57593 | K43: Scenario weighting | L43: Weighted average of base/downside/upside scenarios | M43: IFRS 9 forward-looking adjustment | N43: 1019.268
B44: Coverage Gap: Provisions − EL (€m) | C44: =C42-C43 -> 915.307 | D44: =D42-D43 -> 605.42414 | E44: =E42-E43 -> 763.87105 | F44: =F42-F43 -> 671.3067 | G44: =G42-G43 -> 466.95614 | H44: =H42-H43 -> 334.42407 | K44: Management overlay / PMAs | L44: Post model adjustments | M44: Known model limitations, novel risks, prudence | N44: 294
B45: Coverage Ratio (Provisions / Model EL) | C45: =C42/C43 -> 1.5455748 | D45: =D42/D43 -> 1.4456315 | E45: =E42/E43 -> 1.8194908 | F45: =F42/F43 -> 1.7395744 | G45: =G42/G43 -> 1.4999296 | H45: =H42/H43 -> 1.3904196 | K45: Stage effects | L45: Stage 1 / Stage 2 / Stage 3 / POCI treatment | M45: 12m vs lifetime ECL differences | N45: —
K46: Final reconciled ECL | L46: Reported ECL allowance | M46: Comparable to AIB reported total ECL | N46: 1191

Sheet Macro Regression
B1: MACRO-LINKED PD ESTIMATION | OLS: NPL = α + β₁(Unemp) + β₂(GDP) + β₃(Rate) + β₄(HPI) + ε | 2020–2025 | M1: SUMMARY OUTPUT
B3: A. REGRESSION INPUT DATA (Y = Group NPL Ratio; X = Macro Variables) | Now includes 2025 | M3: Regression Statistics
B4: Year | C4: NPL Ratio (Y) | D4: Unemployment (X1) | E4: Modified GNI at constant Market growth | F4: ECB Rate (X3) | G4: House Price (X4) | M4: Multiple R | N4: 0.99974779
B5: 2020 | C5: ='Raw Data'!C31 -> 0.060991421 | D5: 0.0574 | E5: =('Macro(5y Avg)'!C48-'Macro(5y Avg)'!C47)/'Macro(5y Avg)'!C47 -> -0.024522798 | F5: 0 | G5: 0.0031 | M5: R Square | N5: 0.99949564
B6: 2021 | C6: ='Raw Data'!D31 -> 0.043317376 | D6: 0.061167 | E6: =('Macro(5y Avg)'!C49-'Macro(5y Avg)'!C48)/'Macro(5y Avg)'!C48 -> 0.13762714 | F6: 0 | G6: 0.0827 | M6: Adjusted R Square | N6: 0.9974782
B7: 2022 | C7: ='Raw Data'!E31 -> 0.028408204 | D7: 0.0468 | E7: =('Macro(5y Avg)'!C50-'Macro(5y Avg)'!C49)/'Macro(5y Avg)'!C49 -> 0.032757607 | F7: 0.02 | G7: 0.1231 | M7: Standard Error | N7: 0.00077787767
B8: 2023 | C8: ='Raw Data'!F31 -> 0.02547581 | D8: 0.0428 | E8: =('Macro(5y Avg)'!C51-'Macro(5y Avg)'!C50)/'Macro(5y Avg)'!C50 -> 0.056541663 | F8: 0.045 | G8: 0.0307 | M8: Observations | N8: 6
B9: 2024 | C9: ='Raw Data'!G31 -> 0.024503192 | D9: 0.04267 | E9: =('Macro(5y Avg)'!C52-'Macro(5y Avg)'!C51)/'Macro(5y Avg)'!C51 -> 0.047854015 | F9: 0.04 | G9: 0.0852
B10: 2025 | C10: ='Raw Data'!H31 -> 0.020199341 | D10: 0.0443 | E10: =('Macro(5y Avg)'!C53-'Macro(5y Avg)'!C52)/'Macro(5y Avg)'!C52 -> 0.024 | F10: 0.025 | G10: 0.0755 | M10: ANOVA
N11: df | O11: SS | P11: MS | Q11: F | R11: Significance F
M12: Regression | N12: 4 | O12: 0.0011991194 | P12: 0.00029977984 | Q12: 495.42716 | R12: 0.033681296
B13: C. FITTED vs ACTUAL (Model Validation) | M13: Residual | N13: 1 | O13: 6.0509367e-07 | P13: 6.0509367e-07
B14: Year | C14: Actual NPL | D14: Fitted NPL | E14: Residual (pp) | F14: Fit Quality | M14: Total | N14: 5 | O14: 0.0011997245
B15: 2020 | C15: ='Raw Data'!C31 -> 0.060991421 | D15: =$N$17+$N$18*D5+$N$19*E5+$N$20*F5+$N$21*G5 -> 0.061026921 | E15: =C15-D15 -> -3.5500036e-05 | F15: ✓ Good
B16: 2021 | C16: ='Raw Data'!D31 -> 0.043317376 | D16: =$N$17+$N$18*D6+$N$19*E6+$N$20*F6+$N$21*G6 -> 0.043365811 | E16: =C16-D16 -> -4.8434311e-05 | F16: ✓ Good | N16: Coefficients | O16: Standard Error | P16: t Stat | Q16: P-value | R16: Lower 95% | S16: Upper 95% | T16: Lower 95% | U16: Upper 95%
B17: 2022 | C17: ='Raw Data'!E31 -> 0.028408204 | D17: =$N$17+$N$18*D7+$N$19*E7+$N$20*F7+$N$21*G7 -> 0.02799876 | E17: =C17-D17 -> 0.00040944363 | F17: ✓ Good | M17: Intercept | N17: -0.22443468 | O17: 0.018235542 | P17: -12.307541 | Q17: 0.051612615 | R17: -0.45613921 | S17: 0.0072698524 | T17: -0.45613921 | U17: 0.0072698524
B18: 2023 | C18: ='Raw Data'!F31 -> 0.02547581 | D18: =$N$17+$N$18*D8+$N$19*E8+$N$20*F8+$N$21*G8 -> 0.025100327 | E18: =C18-D18 -> 0.00037548363 | F18: ✓ Good | M18: Unemployment (X1) | N18: 4.8577889 | O18: 0.31263176 | P18: 15.538373 | Q18: 0.040914389 | R18: 0.88542568 | S18: 8.830152 | T18: 0.88542568 | U18: 8.830152
B19: 2024 | C19: ='Raw Data'!G31 -> 0.024503192 | D19: =$N$17+$N$18*D9+$N$19*E9+$N$20*F9+$N$21*G9 -> 0.025007246 | E19: =C19-D19 -> -0.0005040542 | F19: ✓ Good | M19: Modified GNI at constant Market growth | N19: -0.26023312 | O19: 0.017662253 | P19: -14.733857 | Q19: 0.043141787 | R19: -0.48465333 | S19: -0.035812916 | T19: -0.48465333 | U19: -0.035812916
B20: 2025 | C20: ='Raw Data'!H31 -> 0.020199341 | D20: =$N$17+$N$18*D10+$N$19*E10+$N$20*F10+$N$21*G10 -> 0.02039628 | E20: =C20-D20 -> -0.00019693871 | F20: ✓ Good | M20: ECB Rate (X3) | N20: 1.1984537 | O20: 0.11790074 | P20: 10.164938 | Q20: 0.062428108 | R20: -0.29961721 | S20: 2.6965246 | T20: -0.29961721 | U20: 2.6965246
M21: House Price (X4) | N21: 0.078346548 | O21: 0.018211444 | P21: 4.3020502 | Q21: 0.14539854 | R21: -0.15305179 | S21: 0.30974489 | T21: -0.15305179 | U21: 0.30974489
B23: D. FORWARD NPL FORECAST (blue cells = inputs — change to run scenarios)
B24: Variable | C24: 100% Base | D24: 100% Downside 1 (Escalating Tensions) | E24: 100% Downside 2 (Trade War/FDI Shock) | F24: 100% Upside (Easing Tensions)
B25: Unemployment (%) | C25: ='Macro(5y Avg)'!C9/100 -> 0.05 | D25: ='Macro(5y Avg)'!D9/100 -> 0.073 | E25: ='Macro(5y Avg)'!E9/100 -> 0.087 | F25: ='Macro(5y Avg)'!F9/100 -> 0.044 | M25: RESIDUAL OUTPUT
B26: GDP Growth (%) | C26: ='Macro(5y Avg)'!C7/100 -> 0.03 | D26: ='Macro(5y Avg)'!D7/100 -> 0.024 | E26: ='Macro(5y Avg)'!E7/100 -> 0.009 | F26: ='Macro(5y Avg)'!F7/100 -> 0.038
B27: ECB Rate (%) | C27: 0.025 | D27: 0.015 | E27: 0.01 | F27: 0.04 | M27: Observation | N27: Predicted NPL Ratio (Y) | O27: Residuals
B28: House Price Chg (%) | C28: ='Macro(5y Avg)'!C8/100 -> 0.021 | D28: ='Macro(5y Avg)'!D8/100 -> 0.001 | E28: ='Macro(5y Avg)'!E8/100 -> -0.041 | F28: ='Macro(5y Avg)'!F8/100 -> 0.042 | M28: 1 | N28: 0.061026921 | O28: -3.5500036e-05
B29: FORECAST NPL RATIO | C29: =$N$17+$N$18*C25+$N$19*C26+$N$20*C27+$N$21*C28 -> 0.042254391 | D29: =$N$17+$N$18*D25+$N$19*D26+$N$20*D27+$N$21*D28 -> 0.14199347 | E29: =$N$17+$N$18*E25+$N$19*E26+$N$20*E27+$N$21*E28 -> 0.20462318 | F29: =$N$17+$N$18*F25+$N$19*F26+$N$20*F27+$N$21*F28 -> 0.030647876 | M29: 2 | N29: 0.043365811 | O29: -4.8434311e-05
M30: 3 | N30: 0.02799876 | O30: 0.00040944363
M31: 4 | N31: 0.025100327 | O31: 0.00037548363
M32: 5 | N32: 0.025007246 | O32: -0.0005040542
M33: 6 | N33: 0.02039628 | O33: -0.00019693871

Sheet Stress Testing
B2: Multiplier
B3: Segment | C3: 100% Base(2026) | D3: 100% Downside 1 (Escalating Tensions) | E3: 100% Downside 2 (Trade War/FDI Shock) | F3: 100% Upside (Easing Tensions) | H3: Key Model Assumptions • LGD held constant • EAD held constant • RWA assumed stable • PD stressed using macro multipliers • CET1 requirement fixed at 11.29% • Simplified top-down IFRS9 framework
B4: Residential Mortgages | C4: ='Macro Forcast(5y)'!Q6/'Macro Forcast(5y)'!$Q6 -> 1 | D4: ='Macro Forcast(5y)'!R6/'Macro Forcast(5y)'!$Q6 -> 1.36 | E4: ='Macro Forcast(5y)'!S6/'Macro Forcast(5y)'!$Q6 -> 2.8466667 | F4: ='Macro Forcast(5y)'!T6/'Macro Forcast(5y)'!$Q6 -> 0.9
B5: Other Personal | C5: ='Macro Forcast(5y)'!Q7/'Macro Forcast(5y)'!$Q7 -> 1 | D5: ='Macro Forcast(5y)'!R7/'Macro Forcast(5y)'!$Q7 -> 1.1393443 | E5: ='Macro Forcast(5y)'!S7/'Macro Forcast(5y)'!$Q7 -> 1.3770492 | F5: ='Macro Forcast(5y)'!T7/'Macro Forcast(5y)'!$Q7 -> 0.95901639
B6: Property & Construction | C6: ='Macro Forcast(5y)'!Q8/'Macro Forcast(5y)'!$Q8 -> 1 | D6: ='Macro Forcast(5y)'!R8/'Macro Forcast(5y)'!$Q8 -> 1.2329114 | E6: ='Macro Forcast(5y)'!S8/'Macro Forcast(5y)'!$Q8 -> 1.4835443 | F6: ='Macro Forcast(5y)'!T8/'Macro Forcast(5y)'!$Q8 -> 0.90379747
B7: Non-Property Business(SME) | C7: ='Macro Forcast(5y)'!Q9/'Macro Forcast(5y)'!$Q9 -> 1 | D7: ='Macro Forcast(5y)'!R9/'Macro Forcast(5y)'!$Q9 -> 1.4159292 | E7: ='Macro Forcast(5y)'!S9/'Macro Forcast(5y)'!$Q9 -> 2.0648968 | F7: ='Macro Forcast(5y)'!T9/'Macro Forcast(5y)'!$Q9 -> 0.92330383
B8: Non-Property Business(Corporate other) | C8: 1 | D8: 1.4159292 | E8: 2.0648968 | F8: 0.92330383
B11: Segment | C11: PD Inputs of 2025 | D11: 100% Downside 1 (Escalating Tensions) | E11: 100% Downside 2 (Trade War/FDI Shock) | F11: 100% Upside (Easing Tensions) | G11: Stress scenarios are applied through PD migration multipliers while LGD and EAD are assumed constant. This reflects a simplified top-down IFRS9 stress testing framework
B12: Residential Mortgages | C12: 0.0165 | D12: =$C12*D4 -> 0.02244 | E12: =$C12*E4 -> 0.04697 | F12: =$C12*F4 -> 0.01485
B13: Other Personal | C13: 0.014812529 | D13: =$C13*D5 -> 0.01687657 | E13: =$C13*E5 -> 0.020397581 | F13: =$C13*F5 -> 0.014205458
B14: Property & Construction | C14: 0.035734706 | D14: =$C14*D6 -> 0.044057726 | E14: =$C14*E6 -> 0.053014019 | F14: =$C14*F6 -> 0.032296936
B15: Non-Property Business(SME) | C15: 0.016480464 | D15: =$C15*D7 -> 0.023335171 | E15: =$C15*E7 -> 0.034030457 | F15: =$C15*F7 -> 0.015216476
B16: Non-Property Business(Corporate other) | C16: 0.0418 | D16: =$C16*D8 -> 0.059185841 | E16: =$C16*E8 -> 0.086312684 | F16: =$C16*F8 -> 0.0385941
K17: RWA | L17: ='Macro(5y Avg)'!C24 -> 58693
K18: CET1 | L18: ='Macro(5y Avg)'!C30 -> 0.162
K19: CET1 Capital | L19: =L18*L17 -> 9508.266
B20: Segment | C20: Base EL Loss | D20: 100% Downside 1 (Escalating Tensions) | E20: 100% Downside 2 (Trade War/FDI Shock) | F20: 100% Upside (Easing Tensions) | G20: SCENARIO WEIGHTED ECL | H20: CAPITAL IMPACT | I20: % Increase vs Base
B21: Residential Mortgages | C21: =C12*'EL Loss model'!$H15*'EL Loss model'!$H24 -> 211.8998 | D21: =D12*'EL Loss model'!$H15*'EL Loss model'!$H24 -> 288.18373 | E21: =E12*'EL Loss model'!$H15*'EL Loss model'!$H24 -> 603.20809 | F21: =F12*'EL Loss model'!$H15*'EL Loss model'!$H24 -> 190.70982 | G21: =C21*'Macro Forcast(5y)'!$C$29+'Stress Testing'!D21*'Macro Forcast(5y)'!$C$30+'Stress Testing'!E21*'Macro Forcast(5y)'!$C$31+'Stress Testing'!F21*'Macro Forcast(5y)'!$C$32 -> 260.91928 | H21: =G21-C21 -> 49.019487 | I21: =H21/C21 -> 0.23133333
B22: Other Personal | C22: =C13*'EL Loss model'!$H16*'EL Loss model'!$H25 -> 62 | D22: =D13*'EL Loss model'!$H16*'EL Loss model'!$H25 -> 70.639344 | E22: =E13*'EL Loss model'!$H16*'EL Loss model'!$H25 -> 85.377049 | F22: =F13*'EL Loss model'!$H16*'EL Loss model'!$H25 -> 59.459016 | G22: =C22*'Macro Forcast(5y)'!$C$29+'Stress Testing'!D22*'Macro Forcast(5y)'!$C$30+'Stress Testing'!E22*'Macro Forcast(5y)'!$C$31+'Stress Testing'!F22*'Macro Forcast(5y)'!$C$32 -> 66.497541 | H22: =G22-C22 -> 4.497541 | I22: =H22/C22 -> 0.072540984
B23: Property & Construction | C23: =C14*'EL Loss model'!$H17*'EL Loss model'!$H26 -> 160.35 | D23: =D14*'EL Loss model'!$H17*'EL Loss model'!$H26 -> 197.69734 | E23: =E14*'EL Loss model'!$H17*'EL Loss model'!$H26 -> 237.88633 | F23: =F14*'EL Loss model'!$H17*'EL Loss model'!$H26 -> 144.92392 | G23: =C23*'Macro Forcast(5y)'!$C$29+'Stress Testing'!D23*'Macro Forcast(5y)'!$C$30+'Stress Testing'!E23*'Macro Forcast(5y)'!$C$31+'Stress Testing'!F23*'Macro Forcast(5y)'!$C$32 -> 178.39445 | H23: =G23-C23 -> 18.044449 | I23: =H23/C23 -> 0.11253165
B24: Non-Property Business(SME) | C24: =C15*'EL Loss model'!$H18*'EL Loss model'!$H27 -> 119.5893 | D24: =D15*'EL Loss model'!$H18*'EL Loss model'!$H27 -> 169.32998 | E24: =E15*'EL Loss model'!$H18*'EL Loss model'!$H27 -> 246.93956 | F24: =F15*'EL Loss model'!$H18*'EL Loss model'!$H27 -> 110.41726 | G24: =C24*'Macro Forcast(5y)'!$C$29+'Stress Testing'!D24*'Macro Forcast(5y)'!$C$30+'Stress Testing'!E24*'Macro Forcast(5y)'!$C$31+'Stress Testing'!F24*'Macro Forcast(5y)'!$C$32 -> 145.39448 | H24: =G24-C24 -> 25.805184 | I24: =H24/C24 -> 0.21578171
B25: Non-Property Business(Corporate other) | C25: =C16*'EL Loss model'!$H19*'EL Loss model'!$H28 -> 302.73683 | D25: =D16*'EL Loss model'!$H19*'EL Loss model'!$H28 -> 428.65392 | E25: =E16*'EL Loss model'!$H19*'EL Loss model'!$H28 -> 625.12031 | F25: =F16*'EL Loss model'!$H19*'EL Loss model'!$H28 -> 279.51808 | G25: =C25*'Macro Forcast(5y)'!$C$29+'Stress Testing'!D25*'Macro Forcast(5y)'!$C$30+'Stress Testing'!E25*'Macro Forcast(5y)'!$C$31+'Stress Testing'!F25*'Macro Forcast(5y)'!$C$32 -> 368.06191 | H25: =G25-C25 -> 65.325072 | I25: =H25/C25 -> 0.21578171
B26: TOTAL STRESSED EL (€m) | C26: =SUM(C21:C25) -> 856.57593 | D26: =SUM(D21:D25) -> 1154.5043 | E26: =SUM(E21:E25) -> 1798.5313 | F26: =SUM(F21:F25) -> 785.0281 | G26: =SUM(G21:G25) -> 1019.2677 | H26: =G26-C26 -> 162.69173 | I26: =H26/C26 -> 0.18993265
B29: Scenario | C29: Weight | D29: ECL (€m) | E29: Δ vs Base (€m) | F29: Post Stress CET1 Capital | G29: CET1 Post Stress | H29: CET1 Requirement(€m) | I29: Headroom vs CET1 Requirement | J29: RAG | K29: Key Risk
B30: Base | C30: ='Macro Forcast(5y)'!C29 -> 0.5 | D30: =C26 -> 856.57593 | E30: =D30-$D$30 -> 0 | F30: =$L$19-E30 -> 9508.266 | G30: =F30/$L$17 -> 0.162 | H30: ='Macro(5y Avg)'!$C$40 -> 0.1129 | I30: =G30-'Macro(5y Avg)'!$C$40 -> 0.0491 | J30: 🟢 Stable | K30: Stable economy
B31: Downside 1 | C31: ='Macro Forcast(5y)'!C30 -> 0.4 | D31: =D26 -> 1154.5043 | E31: =D31-$D$30 -> 297.92839 | F31: =$L$19-E31 -> 9210.3376 | G31: =F31/$L$17 -> 0.15692395 | H31: ='Macro(5y Avg)'!$C$40 -> 0.1129 | I31: =G31-'Macro(5y Avg)'!$C$40 -> 0.044023954 | J31: 🟡 Monitor | K31: Geopolitical slowdown
B32: Downside 2 | C32: ='Macro Forcast(5y)'!C31 -> 0.05 | D32: =E26 -> 1798.5313 | E32: =D32-$D$30 -> 941.9554 | F32: =$L$19-E32 -> 8566.3106 | G32: =F32/$L$17 -> 0.14595115 | H32: ='Macro(5y Avg)'!$C$40 -> 0.1129 | I32: =G32-'Macro(5y Avg)'!$C$40 -> 0.033051146 | J32: 🔴 Severe Stress | K32: Severe recession
B33: Upside | C33: ='Macro Forcast(5y)'!C32 -> 0.05 | D33: =F26 -> 785.0281 | E33: =D33-$D$30 -> -71.547834 | F33: =$L$19-E33 -> 9579.8138 | G33: =F33/$L$17 -> 0.16321902 | H33: ='Macro(5y Avg)'!$C$40 -> 0.1129 | I33: =G33-'Macro(5y Avg)'!$C$40 -> 0.050319018 | J33: 🟢 Recovery | K33: Recovery scenario
B34: Weighted Avg | C34: =SUM(C30:C33) -> 1 | D34: =G26 -> 1019.2677 | K34: Probability-weighted IFRS9 ECL

Sheet PSI Analysis
B1: PSI ANALYSIS | Portfolio Stability Index | Baseline 2020
B3: A. STAGE DISTRIBUTION PSI vs 2020 BASELINE
B4: Stage | C4: 2020 | D4: =C4+1 -> 2021 | E4: =D4+1 -> 2022 | F4: =E4+1 -> 2023 | G4: =F4+1 -> 2024 | H4: =G4+1 -> 2025
B5: Stage 1 | C5: ='Raw Data'!C63/'Raw Data'!C$11 -> 0.79186781 | D5: ='Raw Data'!D63/'Raw Data'!D$11 -> 0.85233025 | E5: ='Raw Data'!E63/'Raw Data'!E$11 -> 0.87901463 | F5: ='Raw Data'!F63/'Raw Data'!F$11 -> 0.86900026 | G5: ='Raw Data'!G63/'Raw Data'!G$11 -> 0.86948116 | H5: ='Raw Data'!H63/'Raw Data'!H$11 -> 0.87809675
B6: Stage 2 | C6: ='Raw Data'!C64/'Raw Data'!C$11 -> 0.14714077 | D6: ='Raw Data'!D64/'Raw Data'!D$11 -> 0.10435237 | E6: ='Raw Data'!E64/'Raw Data'!E$11 -> 0.092577169 | F6: ='Raw Data'!F64/'Raw Data'!F$11 -> 0.10552393 | G6: ='Raw Data'!G64/'Raw Data'!G$11 -> 0.10601565 | H6: ='Raw Data'!H64/'Raw Data'!H$11 -> 0.10170391
B7: Stage 3 | C7: ='Raw Data'!C65/'Raw Data'!C$11 -> 0.05845356 | D7: ='Raw Data'!D65/'Raw Data'!D$11 -> 0.041900517 | E7: ='Raw Data'!E65/'Raw Data'!E$11 -> 0.02727604 | F7: ='Raw Data'!F65/'Raw Data'!F$11 -> 0.023915581 | G7: ='Raw Data'!G65/'Raw Data'!G$11 -> 0.022322633 | H7: ='Raw Data'!H65/'Raw Data'!H$11 -> 0.018365047
B8: TOTAL PSI | C8: =((C$5-$C$5)*LN(C$5/$C$5))+((C$6-$C$6)*LN(C$6/$C$6))+((C$7-$C$7)*LN(C$7/$C$7)) -> 0 | D8: =((D$5-$C$5)*LN(D$5/$C$5))+((D$6-$C$6)*LN(D$6/$C$6))+((D$7-$C$7)*LN(D$7/$C$7)) -> 0.024662674 | E8: =((E$5-$C$5)*LN(E$5/$C$5))+((E$6-$C$6)*LN(E$6/$C$6))+((E$7-$C$7)*LN(E$7/$C$7)) -> 0.058144885 | F8: =((F$5-$C$5)*LN(F$5/$C$5))+((F$6-$C$6)*LN(F$6/$C$6))+((F$7-$C$7)*LN(F$7/$C$7)) -> 0.051871659 | G8: =((G$5-$C$5)*LN(G$5/$C$5))+((G$6-$C$6)*LN(G$6/$C$6))+((G$7-$C$7)*LN(G$7/$C$7)) -> 0.055518728 | H8: =((H$5-$C$5)*LN(H$5/$C$5))+((H$6-$C$6)*LN(H$6/$C$6))+((H$7-$C$7)*LN(H$7/$C$7)) -> 0.072107563
B9: Status | D9: =IF(D8<0.1,"Stable",IF(D8<0.25,"Monitor","Major Shift")) -> Stable | E9: =IF(E8<0.1,"Stable",IF(E8<0.25,"Monitor","Major Shift")) -> Stable | F9: =IF(F8<0.1,"Stable",IF(F8<0.25,"Monitor","Major Shift")) -> Stable | G9: =IF(G8<0.1,"Stable",IF(G8<0.25,"Monitor","Major Shift")) -> Stable | H9: =IF(H8<0.1,"Stable",IF(H8<0.25,"Monitor","Major Shift")) -> Stable
B12: B. Portfolio Segment Distribution & PSI Stability (2020–2025)
B13: Segment | C13: 2020 | D13: =C13+1 -> 2021 | E13: =D13+1 -> 2022 | F13: =E13+1 -> 2023 | G13: =F13+1 -> 2024 | H13: =G13+1 -> 2025
B14: Residential Mortgages | C14: ='Raw Data'!C6/'Raw Data'!C$11 -> 0.43427768 | D14: ='Raw Data'!D6/'Raw Data'!D11 -> 0.42164631 | E14: ='Raw Data'!E6/'Raw Data'!E11 -> 0.40923169 | F14: ='Raw Data'!F6/'Raw Data'!F11 -> 0.42876539 | G14: ='Raw Data'!G6/'Raw Data'!G11 -> 0.43326814 | H14: ='Raw Data'!H6/'Raw Data'!H11 -> 0.43028575
B15: Other Personal | C15: ='Raw Data'!C7/'Raw Data'!C$11 -> 0.077721994 | D15: ='Raw Data'!D7/'Raw Data'!D$11 -> 0.076482888 | E15: ='Raw Data'!E7/'Raw Data'!E$11 -> 0.072731768 | F15: ='Raw Data'!F7/'Raw Data'!F$11 -> 0.069864939 | G15: ='Raw Data'!G7/'Raw Data'!G$11 -> 0.070261218 | H15: ='Raw Data'!H7/'Raw Data'!H$11 -> 0.071614842
B16: Property & Construction | C16: ='Raw Data'!C8/'Raw Data'!C$11 -> 0.12689305 | D16: ='Raw Data'!D8/'Raw Data'!D$11 -> 0.13377627 | E16: ='Raw Data'!E8/'Raw Data'!E$11 -> 0.14316017 | F16: ='Raw Data'!F8/'Raw Data'!F$11 -> 0.13650223 | G16: ='Raw Data'!G8/'Raw Data'!G$11 -> 0.12211132 | H16: ='Raw Data'!H8/'Raw Data'!H$11 -> 0.11595836
B17: Non-Property Business(SME) | C17: ='Raw Data'!C9/'Raw Data'!C$11 -> 0.25117928 | D17: ='Raw Data'!D9/'Raw Data'!D$11 -> 0.24960108 | E17: ='Raw Data'!E9/'Raw Data'!E$11 -> 0.18139347 | F17: ='Raw Data'!F9/'Raw Data'!F$11 -> 0.17476954 | G17: ='Raw Data'!G9/'Raw Data'!G$11 -> 0.17677142 | H17: ='Raw Data'!H9/'Raw Data'!H$11 -> 0.17902053
B18: Non-Property Business(Corporate other) | C18: ='Raw Data'!C10/'Raw Data'!C$11 -> 0.109928 | D18: ='Raw Data'!D10/'Raw Data'!D$11 -> 0.11849345 | E18: ='Raw Data'!E10/'Raw Data'!E$11 -> 0.1934829 | F18: ='Raw Data'!F10/'Raw Data'!F$11 -> 0.1900979 | G18: ='Raw Data'!G10/'Raw Data'!G$11 -> 0.1975879 | H18: ='Raw Data'!H10/'Raw Data'!H$11 -> 0.20312051
B19: TOTAL PSI | C19: =((C$14-$C$14)*LN(C$14/$C$14))+((C$15-$C$15)*LN(C$15/$C$15))+((C$16-$C$16)*LN(C$16/$C$16))+((C$17-$C$17)*LN(C$17/$C$17))+((C$18-$C$18)*LN(C$18/$C$18)) -> 0 | D19: =((D$14-$C$14)*LN(D$14/$C$14))+((D$15-$C$15)*LN(D$15/$C$15))+((D$16-$C$16)*LN(D$16/$C$16))+((D$17-$C$17)*LN(D$17/$C$17))+((D$18-$C$18)*LN(D$18/$C$18)) -> 0.0014089895 | E19: =((E$14-$C$14)*LN(E$14/$C$14))+((E$15-$C$15)*LN(E$15/$C$15))+((E$16-$C$16)*LN(E$16/$C$16))+((E$17-$C$17)*LN(E$17/$C$17))+((E$18-$C$18)*LN(E$18/$C$18)) -> 0.073735138 | F19: =((F$14-$C$14)*LN(F$14/$C$14))+((F$15-$C$15)*LN(F$15/$C$15))+((F$16-$C$16)*LN(F$16/$C$16))+((F$17-$C$17)*LN(F$17/$C$17))+((F$18-$C$18)*LN(F$18/$C$18)) -> 0.07323307 | G19: =((G$14-$C$14)*LN(G$14/$C$14))+((G$15-$C$15)*LN(G$15/$C$15))+((G$16-$C$16)*LN(G$16/$C$16))+((G$17-$C$17)*LN(G$17/$C$17))+((G$18-$C$18)*LN(G$18/$C$18)) -> 0.078479206 | H19: =((H$14-$C$14)*LN(H$14/$C$14))+((H$15-$C$15)*LN(H$15/$C$15))+((H$16-$C$16)*LN(H$16/$C$16))+((H$17-$C$17)*LN(H$17/$C$17))+((H$18-$C$18)*LN(H$18/$C$18)) -> 0.083177518
B20: Status | D20: =IF(D19<0.1,"Stable",IF(D19<0.25,"Monitor","Major Shift")) -> Stable | E20: =IF(E19<0.1,"Stable",IF(E19<0.25,"Monitor","Major Shift")) -> Stable | F20: =IF(F19<0.1,"Stable",IF(F19<0.25,"Monitor","Major Shift")) -> Stable | G20: =IF(G19<0.1,"Stable",IF(G19<0.25,"Monitor","Major Shift")) -> Stable | H20: =IF(H19<0.1,"Stable",IF(H19<0.25,"Monitor","Major Shift")) -> Stable

Sheet Data->

Sheet 2025
A1: AIB Annual 2025
A4: Concentration by industry sector | B4: Loans (€m) | C4: Off-Bal (€m) | D4: Total Gross (€m) | E4: Stage 1 (€m) | F4: Stage 2 (€m) | G4: Stage 3 (€m) | H4: POCI (€m) | I4: Total Alloc (€m) | L4: Loans (€m) | M4: Off-Bal (€m) | N4: Total Gross (€m) | O4: Stage 1 (€m) | P4: Stage 2 (€m) | Q4: Stage 3 (€m) | R4: POCI (€m)
A5: Non-property business: | K5: Non-Property Business(Corporate other)
A6: Natural resources | B6: 5443 | C6: 2099 | D6: 7542 | E6: 6543 | F6: 942 | G6: 57 | H6: 0 | I6: 7542 | K6: Natural resources | L6: 5443 | M6: 2099 | N6: 7542 | O6: 6543 | P6: 942 | Q6: 57 | R6: 0
A7: Of which renewables | B7: 4972 | C7: 1379 | D7: 6351 | E7: 5408 | F7: 893 | G7: 50 | H7: 0 | I7: 6351 | K7: Manufacturing | L7: 2894 | M7: 2323 | N7: 5217 | O7: 4319 | P7: 830 | Q7: 67 | R7: 1
A8: Leisure | B8: 2796 | C8: 448 | D8: 3244 | E8: 2754 | F8: 438 | G8: 50 | H8: 2 | I8: 3244 | K8: Health, education and social work | L8: 1887 | M8: 392 | N8: 2279 | O8: 2017 | P8: 248 | Q8: 14 | R8: 0
A9: Manufacturing | B9: 2894 | C9: 2323 | D9: 5217 | E9: 4319 | F9: 830 | G9: 67 | H9: 1 | I9: 5217 | K9: Telecommunications, media and tech | L9: 1444 | M9: 397 | N9: 1841 | O9: 1431 | P9: 206 | Q9: 204 | R9: 0
A10: Health, education and social work | B10: 1887 | C10: 392 | D10: 2279 | E10: 2017 | F10: 248 | G10: 14 | H10: 0 | I10: 2279 | K10: Financial, insurance and govt | L10: 446 | M10: 1057 | N10: 1503 | O10: 1471 | P10: 31 | Q10: 1 | R10: 0
A11: Services | B11: 2458 | C11: 1630 | D11: 4088 | E11: 3713 | F11: 321 | G11: 52 | H11: 2 | I11: 4088 | K11: Non-Property Business(SME) | M11: SUM= | N11: =SUM(N6:N10) -> 18382 | Q11: =SUM(Q6:Q10) -> 343 | R11: =SUM(R6:R10) -> 1
A12: Agriculture, forestry and fishing | B12: 1634 | C12: 677 | D12: 2311 | E12: 1823 | F12: 405 | G12: 78 | H12: 5 | I12: 2311 | K12: Leisure | L12: 2796 | M12: 448 | N12: 3244 | O12: 2754 | P12: 438 | Q12: 50 | R12: 2
A13: Retail and wholesale trade | B13: 2059 | C13: 1911 | D13: 3970 | E13: 3395 | F13: 518 | G13: 53 | H13: 4 | I13: 3970 | K13: Agriculture, forestry and fishing | L13: 1634 | M13: 677 | N13: 2311 | O13: 1823 | P13: 405 | Q13: 78 | R13: 5
A14: Transport and storage | B14: 1839 | C14: 749 | D14: 2588 | E14: 2382 | F14: 185 | G14: 20 | H14: 1 | I14: 2588 | K14: Retail and wholesale trade | L14: 2059 | M14: 1911 | N14: 3970 | O14: 3395 | P14: 518 | Q14: 53 | R14: 4
A15: Telecommunications, media and tech | B15: 1444 | C15: 397 | D15: 1841 | E15: 1431 | F15: 206 | G15: 204 | H15: 0 | I15: 1841 | K15: Services | L15: 2458 | M15: 1630 | N15: 4088 | O15: 3713 | P15: 321 | Q15: 52 | R15: 2
A16: Financial, insurance and govt | B16: 446 | C16: 1057 | D16: 1503 | E16: 1471 | F16: 31 | G16: 1 | H16: 0 | I16: 1503 | K16: Transport and storage | L16: 1839 | M16: 749 | N16: 2588 | O16: 2382 | P16: 185 | Q16: 20 | R16: 1
A17: Total non-property business | B17: 22900 | C17: 11683 | D17: 34583 | E17: 29848 | F17: 4124 | G17: 596 | H17: 15 | I17: 34583 | M17: SUM= | N17: =SUM(N12:N16) -> 16201 | Q17: =SUM(Q12:Q16) -> 253 | R17: =SUM(R12:R16) -> 14
A18: Property and construction | B18: 8389 | C18: 2105 | D18: 10494 | E18: 7565 | F18: 2554 | G18: 374 | H18: 1 | I18: 10494
A19: Residential mortgages | B19: 37531 | C19: 1409 | D19: 38940 | E19: 36399 | F19: 1795 | G19: 596 | H19: 150 | I19: 38940 | M19: Total= | N19: =SUM(N11,N17) -> 34583
A20: Other personal | B20: 3439 | C20: 3042 | D20: 6481 | E20: 5654 | F20: 731 | G20: 96 | H20: 0 | I20: 6481
A21: Total Portfolio | B21: 72259 | C21: 18239 | D21: 90498 | E21: 79466 | F21: 9204 | G21: 1662 | H21: 166 | I21: 90498
A24: ECL Allowance | B24: Loans ECL (€m) | C24: Off-Bal ECL (€m) | D24: Total ECL (€m) | E24: Stage 1 ECL (€m) | F24: Stage 2 ECL (€m) | G24: Stage 3 ECL (€m) | H24: POCI ECL (€m) | I24: Total Alloc ECL (€m) | K24: ECL Allowance | L24: Loans ECL (€m) | M24: Off-Bal ECL (€m) | N24: Total ECL (€m) | O24: Stage 1 ECL (€m) | P24: Stage 2 ECL (€m) | Q24: Stage 3 ECL (€m) | R24: POCI ECL (€m) | S24: Total Alloc ECL (€m)
A25: Non-property business:
A26: Natural resources | B26: 36 | C26: 1 | D26: 37 | E26: 5 | F26: 20 | G26: 12 | H26: 0 | I26: 37 | K26: Non-Property Business(SME)
A27: Of which renewables | B27: 30 | C27: 0 | D27: 30 | E27: 2 | F27: 17 | G27: 11 | H27: 0 | I27: 30 | K27: Natural resources | L27: 36 | M27: 1 | N27: 37 | O27: 5 | P27: 20 | Q27: 12 | R27: 0
A28: Leisure | B28: 85 | C28: 2 | D28: 87 | E28: 14 | F28: 55 | G28: 19 | H28: -1 | I28: 87 | K28: Manufacturing | L28: 42 | M28: 5 | N28: 47 | O28: 8 | P28: 24 | Q28: 16 | R28: -1
A29: Manufacturing | B29: 42 | C29: 5 | D29: 47 | E29: 8 | F29: 24 | G29: 16 | H29: -1 | I29: 47 | K29: Health, education and social work | L29: 20 | M29: 1 | N29: 21 | O29: 6 | P29: 11 | Q29: 4 | R29: 0
A30: Health, education and social work | B30: 20 | C30: 1 | D30: 21 | E30: 6 | F30: 11 | G30: 4 | H30: 0 | I30: 21 | K30: Telecommunications, media and tech | L30: 70 | M30: 4 | N30: 74 | O30: 5 | P30: 16 | Q30: 53 | R30: 0
A31: Services | B31: 34 | C31: 4 | D31: 38 | E31: 9 | F31: 16 | G31: 13 | H31: 0 | I31: 38 | K31: Financial, insurance and govt | L31: 2 | M31: 0 | N31: 2 | O31: 1 | P31: 1 | Q31: 0 | R31: 0
A32: Agriculture, forestry and fishing | B32: 31 | C32: 2 | D32: 33 | E32: 5 | F32: 14 | G32: 18 | H32: -4 | I32: 33 | Q32: =SUM(Q27:Q31) -> 85 | R32: =SUM(R27:R31) -> -1
A33: Retail and wholesale trade | B33: 58 | C33: 7 | D33: 65 | E33: 8 | F33: 37 | G33: 20 | H33: 0 | I33: 65 | K33: Non-Property Business(SME)
A34: Transport and storage | B34: 26 | C34: 1 | D34: 27 | E34: 6 | F34: 9 | G34: 12 | H34: 0 | I34: 27 | K34: Leisure | L34: 85 | M34: 2 | N34: 87 | O34: 14 | P34: 55 | Q34: 19 | R34: -1
A35: Telecommunications, media and tech | B35: 70 | C35: 4 | D35: 74 | E35: 5 | F35: 16 | G35: 53 | H35: 0 | I35: 74 | K35: Services | L35: 34 | M35: 4 | N35: 38 | O35: 9 | P35: 16 | Q35: 13 | R35: 0
A36: Financial, insurance and govt | B36: 2 | C36: 0 | D36: 2 | E36: 1 | F36: 1 | G36: 0 | H36: 0 | I36: 2 | K36: Agriculture, forestry and fishing | L36: 31 | M36: 2 | N36: 33 | O36: 5 | P36: 14 | Q36: 18 | R36: -4
A37: Total non-property business | B37: 404 | C37: 27 | D37: 431 | E37: 67 | F37: 203 | G37: 167 | H37: -6 | I37: 431 | K37: Retail and wholesale trade | L37: 58 | M37: 7 | N37: 65 | O37: 8 | P37: 37 | Q37: 20 | R37: 0
A38: Property and construction | B38: 432 | C38: 14 | D38: 446 | E38: 83 | F38: 218 | G38: 145 | H38: 0 | I38: 446 | K38: Transport and storage | L38: 26 | M38: 1 | N38: 27 | O38: 6 | P38: 9 | Q38: 12 | R38: 0
A39: Residential mortgages | B39: 176 | C39: 0 | D39: 176 | E39: 13 | F39: 48 | G39: 125 | H39: -10 | I39: 176 | Q39: =SUM(Q34:Q38) -> 82 | R39: =SUM(R34:R38) -> -5
A40: Other personal | B40: 131 | C40: 7 | D40: 138 | E40: 23 | F40: 53 | G40: 62 | H40: 0 | I40: 138
A41: Total Portfolio | B41: 1143 | C41: 48 | D41: 1191 | E41: 186 | F41: 522 | G41: 499 | H41: -16 | I41: 1191

Sheet 2024
A1: AIB Annual 2025
A3: Concentration by industry sector | B3: Loans (€m) | C3: Off-Bal (€m) | D3: Total Gross (€m) | E3: Stage 1 (€m) | F3: Stage 2 (€m) | G3: Stage 3 (€m) | H3: POCI (€m) | I3: Total Book (€m) | J3: Fin Guarantees (€m) | M3: Loans (€m) | N3: Off-Bal (€m) | O3: Total Gross (€m) | P3: Stage 1 (€m) | Q3: Stage 2 (€m) | R3: Stage 3 (€m) | S3: POCI (€m)
A4: Non-property business: | L4: Non-Property Business(Corporate other)
A5: Natural resources | B5: 4995 | C5: 2221 | D5: 7216 | E5: 6904 | F5: 294 | G5: 18 | H5: 0 | I5: 7216 | J5: 29 | L5: Natural resources | M5: 4995 | N5: 2221 | O5: 7216 | P5: 6904 | Q5: 294 | R5: 18 | S5: 0
A6: Of which renewables | B6: 4479 | C6: 1506 | D6: 5985 | E6: 5734 | F6: 248 | G6: 3 | H6: 0 | I6: 5985 | J6: 0 | L6: Manufacturing | M6: 2753 | N6: 2234 | O6: 4987 | P6: 4409 | Q6: 537 | R6: 40 | S6: 1
A7: Leisure | B7: 2942 | C7: 490 | D7: 3432 | E7: 2706 | F7: 605 | G7: 118 | H7: 3 | I7: 3432 | J7: 0 | L7: Health, education and social work | M7: 1879 | N7: 358 | O7: 2237 | P7: 1774 | Q7: 442 | R7: 19 | S7: 2
A8: Manufacturing | B8: 2753 | C8: 2234 | D8: 4987 | E8: 4409 | F8: 537 | G8: 40 | H8: 1 | I8: 4987 | J8: 0 | L8: Telecommunications, media and tech | M8: 1450 | N8: 201 | O8: 1651 | P8: 1436 | Q8: 165 | R8: 50 | S8: 0
A9: Health, education and social work | B9: 1879 | C9: 358 | D9: 2237 | E9: 1774 | F9: 442 | G9: 19 | H9: 2 | I9: 2237 | J9: 0 | L9: Financial, insurance and govt | M9: 470 | N9: 1018 | O9: 1488 | P9: 1417 | Q9: 59 | R9: 12 | S9: 0
A10: Services | B10: 2250 | C10: 1311 | D10: 3561 | E10: 3156 | F10: 361 | G10: 41 | H10: 3 | I10: 3561 | J10: 0 | O10: =SUM(O5:O9) -> 17579 | R10: =SUM(R5:R9) -> 139 | S10: =SUM(S5:S9) -> 3
A11: Agriculture, forestry and fishing | B11: 1691 | C11: 685 | D11: 2376 | E11: 1875 | F11: 405 | G11: 89 | H11: 7 | I11: 2376 | J11: 0 | L11: Non-Property Business(SME)
A12: Retail and wholesale trade | B12: 1895 | C12: 1916 | D12: 3811 | E12: 3126 | F12: 617 | G12: 63 | H12: 5 | I12: 3811 | J12: 17 | L12: Leisure | M12: 2942 | N12: 490 | O12: 3432 | P12: 2706 | Q12: 605 | R12: 118 | S12: 3
A13: Transport and storage | B13: 1848 | C13: 699 | D13: 2547 | E13: 2226 | F13: 244 | G13: 77 | H13: 0 | I13: 2547 | J13: 0 | L13: Services | M13: 2250 | N13: 1311 | O13: 3561 | P13: 3156 | Q13: 361 | R13: 41 | S13: 3
A14: Telecommunications, media and tech | B14: 1450 | C14: 201 | D14: 1651 | E14: 1436 | F14: 165 | G14: 50 | H14: 0 | I14: 1651 | J14: 18 | L14: Agriculture, forestry and fishing | M14: 1691 | N14: 685 | O14: 2376 | P14: 1875 | Q14: 405 | R14: 89 | S14: 7
A15: Financial, insurance and govt | B15: 470 | C15: 1018 | D15: 1488 | E15: 1417 | F15: 59 | G15: 12 | H15: 0 | I15: 1488 | J15: 0 | L15: Retail and wholesale trade | M15: 1895 | N15: 1916 | O15: 3811 | P15: 3126 | Q15: 617 | R15: 63 | S15: 5
A16: Total non-property business | B16: 22173 | C16: 11133 | D16: 33306 | E16: 29029 | F16: 3729 | G16: 527 | H16: 21 | I16: 33306 | J16: 64 | L16: Transport and storage | M16: 1848 | N16: 699 | O16: 2547 | P16: 2226 | Q16: 244 | R16: 77 | S16: 0
A17: Property and construction | B17: 8761 | C17: 2103 | D17: 10864 | E17: 7274 | F17: 3013 | G17: 574 | H17: 3 | I17: 10864 | J17: 0 | O17: =SUM(O12:O16) -> 15727 | R17: =SUM(R12:R16) -> 388 | S17: =SUM(S12:S16) -> 18
A18: Residential mortgages | B18: 36970 | C18: 1577 | D18: 38547 | E18: 35731 | F18: 1870 | G18: 776 | H18: 170 | I18: 38547 | J18: 0
A19: Other personal | B19: 3265 | C19: 2986 | D19: 6251 | E19: 5322 | F19: 820 | G19: 109 | H19: 0 | I19: 6251 | J19: 0 | O19: =SUM(O10,O17) -> 33306
A20: Total Portfolio | B20: 71169 | C20: 17799 | D20: 88968 | E20: 77356 | F20: 9432 | G20: 1986 | H20: 194 | I20: 88968 | J20: 64
A24: ECL Allowance | B24: Loans (€m) | C24: Off-Bal (€m) | D24: Total Gross (€m) | E24: Stage 1 (€m) | F24: Stage 2 (€m) | G24: Stage 3 (€m) | H24: POCI (€m) | I24: Total Book (€m) | L24: ECL Allowance | M24: Loans (€m) | N24: Off-Bal (€m) | O24: Total Gross (€m) | P24: Stage 1 (€m) | Q24: Stage 2 (€m) | R24: Stage 3 (€m) | S24: POCI (€m)
A25: Non-property business: | L25: Non-Property Business(Corporate other)
A26: Natural resources | B26: 32 | C26: 2 | D26: 34 | E26: 17 | F26: 15 | G26: 2 | H26: 0 | I26: 34 | L26: Natural resources | M26: 32 | N26: 2 | O26: 34 | P26: 17 | Q26: 15 | R26: 2 | S26: 0
A27: Of which renewables | B27: 23 | C27: 1 | D27: 24 | E27: 15 | F27: 9 | G27: 0 | H27: 0 | I27: 24 | L27: Manufacturing | M27: 59 | N27: 6 | O27: 65 | P27: 10 | Q27: 36 | R27: 19 | S27: 0
A28: Leisure | B28: 86 | C28: 5 | D28: 91 | E28: 21 | F28: 38 | G28: 33 | H28: -1 | I28: 91 | L28: Health, education and social work | M28: 51 | N28: 2 | O28: 53 | P28: 12 | Q28: 37 | R28: 5 | S28: -1
A29: Manufacturing | B29: 59 | C29: 6 | D29: 65 | E29: 10 | F29: 36 | G29: 19 | H29: 0 | I29: 65 | L29: Telecommunications, media and tech | M29: 31 | N29: 1 | O29: 32 | P29: 8 | Q29: 13 | R29: 11 | S29: 0
A30: Health, education and social work | B30: 51 | C30: 2 | D30: 53 | E30: 12 | F30: 37 | G30: 5 | H30: -1 | I30: 53 | L30: Financial, insurance and govt | M30: 14 | N30: 0 | O30: 14 | P30: 2 | Q30: 2 | R30: 10 | S30: 0
A31: Services | B31: 34 | C31: 4 | D31: 38 | E31: 10 | F31: 16 | G31: 12 | H31: 0 | I31: 38 | R31: =SUM(R26:R30) -> 47 | S31: =SUM(S26:S30) -> -1
A32: Agriculture, forestry and fishing | B32: 37 | C32: 3 | D32: 40 | E32: 5 | F32: 16 | G32: 23 | H32: -4 | I32: 40 | L32: Non-Property Business(SME)
A33: Retail and wholesale trade | B33: 56 | C33: 5 | D33: 61 | E33: 10 | F33: 31 | G33: 21 | H33: -1 | I33: 61 | L33: Leisure | M33: 86 | N33: 5 | O33: 91 | P33: 21 | Q33: 38 | R33: 33 | S33: -1
A34: Transport and storage | B34: 73 | C34: 2 | D34: 75 | E34: 8 | F34: 7 | G34: 60 | H34: 0 | I34: 75 | L34: Services | M34: 34 | N34: 4 | O34: 38 | P34: 10 | Q34: 16 | R34: 12 | S34: 0
A35: Telecommunications, media and tech | B35: 31 | C35: 1 | D35: 32 | E35: 8 | F35: 13 | G35: 11 | H35: 0 | I35: 32 | L35: Agriculture, forestry and fishing | M35: 37 | N35: 3 | O35: 40 | P35: 5 | Q35: 16 | R35: 23 | S35: -4
A36: Financial, insurance and govt | B36: 14 | C36: 0 | D36: 14 | E36: 2 | F36: 2 | G36: 10 | H36: 0 | I36: 14 | L36: Retail and wholesale trade | M36: 56 | N36: 5 | O36: 61 | P36: 10 | Q36: 31 | R36: 21 | S36: -1
A37: Total non-property business | B37: 473 | C37: 30 | D37: 503 | E37: 103 | F37: 211 | G37: 196 | H37: -7 | I37: 503 | L37: Transport and storage | M37: 73 | N37: 2 | O37: 75 | P37: 8 | Q37: 7 | R37: 60 | S37: 0
A38: Property and construction | B38: 464 | C38: 20 | D38: 484 | E38: 67 | F38: 230 | G38: 188 | H38: -1 | I38: 484 | R38: =SUM(R33:R37) -> 149 | S38: =SUM(S33:S37) -> -6
A39: Residential mortgages | B39: 270 | C39: 1 | D39: 271 | E39: 11 | F39: 53 | G39: 210 | H39: -3 | I39: 271
A40: Other personal | B40: 137 | C40: 6 | D40: 143 | E40: 20 | F40: 57 | G40: 66 | H40: 0 | I40: 143
A41: Total Portfolio | B41: 1344 | C41: 57 | D41: 1401 | E41: 201 | F41: 551 | G41: 660 | H41: -11 | I41: 1401

Sheet 2023
A1: AIB Annual 2025
A3: Concentration by industry sector | B3: Loans (€m) | C3: Off-Bal (€m) | D3: Total Gross (€m) | E3: Stage 1 (€m) | F3: Stage 2 (€m) | G3: Stage 3 (€m) | H3: POCI (€m) | I3: Total Book (€m) | J3: Fin Guarantees (€m) | M3: Loans (€m) | N3: Off-Bal (€m) | O3: Total Gross (€m) | P3: Stage 1 (€m) | Q3: Stage 2 (€m) | R3: Stage 3 (€m) | S3: POCI (€m)
A4: Non-property business: | L4: Non-Property Business(Corporate other)
A5: Natural resources | B5: 3610 | C5: 2113 | D5: 5723 | E5: 5502 | F5: 198 | G5: 23 | H5: 0 | I5: 5723 | J5: 27 | L5: Natural resources | M5: 3610 | N5: 2113 | O5: 5723 | P5: 5502 | Q5: 198 | R5: 23 | S5: 0
A6: Of which renewables | B6: 2907 | C6: 1133 | D6: 4040 | E6: 3960 | F6: 80 | G6: 0 | H6: 0 | I6: 4040 | J6: 0 | L6: Manufacturing | M6: 2519 | N6: 2179 | O6: 4698 | P6: 4281 | Q6: 375 | R6: 40 | S6: 2
A7: Leisure | B7: 2666 | C7: 555 | D7: 3221 | E7: 2428 | F7: 603 | G7: 185 | H7: 5 | I7: 3221 | J7: 0 | L7: Health, education and social work | M7: 2032 | N7: 385 | O7: 2417 | P7: 1928 | Q7: 448 | R7: 39 | S7: 2
A8: Manufacturing | B8: 2519 | C8: 2179 | D8: 4698 | E8: 4281 | F8: 375 | G8: 40 | H8: 2 | I8: 4698 | J8: 0 | L8: Telecommunications, media and tech | M8: 1394 | N8: 332 | O8: 1726 | P8: 1621 | Q8: 93 | R8: 12 | S8: 0
A9: Health, education and social work | B9: 2032 | C9: 385 | D9: 2417 | E9: 1928 | F9: 448 | G9: 39 | H9: 2 | I9: 2417 | J9: 0 | L9: Financial, insurance and govt | M9: 506 | N9: 891 | O9: 1397 | P9: 1360 | Q9: 26 | R9: 11 | S9: 0
A10: Services | B10: 2064 | C10: 1333 | D10: 3397 | E10: 3103 | F10: 247 | G10: 43 | H10: 4 | I10: 3397 | J10: 0 | O10: =SUM(O5:O9) -> 15961 | R10: =SUM(R5:R9) -> 125 | S10: =SUM(S5:S9) -> 4
A11: Agriculture, forestry and fishing | B11: 1780 | C11: 707 | D11: 2487 | E11: 2071 | F11: 323 | G11: 84 | H11: 9 | I11: 2487 | J11: 0 | L11: Non-Property Business(SME)
A12: Retail and wholesale trade | B12: 1747 | C12: 1516 | D12: 3263 | E12: 2915 | F12: 279 | G12: 63 | H12: 6 | I12: 3263 | J12: 15 | L12: Leisure | M12: 2666 | N12: 555 | O12: 3221 | P12: 2428 | Q12: 603 | R12: 185 | S12: 5
A13: Transport and storage | B13: 1710 | C13: 596 | D13: 2306 | E13: 2094 | F13: 171 | G13: 40 | H13: 1 | I13: 2306 | J13: 0 | L13: Services | M13: 2064 | N13: 1333 | O13: 3397 | P13: 3103 | Q13: 247 | R13: 43 | S13: 4
A14: Telecommunications, media and tech | B14: 1394 | C14: 332 | D14: 1726 | E14: 1621 | F14: 93 | G14: 12 | H14: 0 | I14: 1726 | J14: 0 | L14: Agriculture, forestry and fishing | M14: 1780 | N14: 707 | O14: 2487 | P14: 2071 | Q14: 323 | R14: 84 | S14: 9
A15: Financial, insurance and govt | B15: 506 | C15: 891 | D15: 1397 | E15: 1360 | F15: 26 | G15: 11 | H15: 0 | I15: 1397 | J15: 0 | L15: Retail and wholesale trade | M15: 1747 | N15: 1516 | O15: 3263 | P15: 2915 | Q15: 279 | R15: 63 | S15: 6
A16: Total non-property business | B16: 20028 | C16: 10607 | D16: 30635 | E16: 27303 | F16: 2763 | G16: 540 | H16: 29 | I16: 30635 | J16: 42 | L16: Transport and storage | M16: 1710 | N16: 596 | O16: 2306 | P16: 2094 | Q16: 171 | R16: 40 | S16: 1
A17: Property and construction | B17: 9237 | C17: 2224 | D17: 11461 | E17: 7504 | F17: 3270 | G17: 683 | H17: 4 | I17: 11461 | J17: 0 | O17: =SUM(O12:O16) -> 14674 | R17: =SUM(R12:R16) -> 415 | S17: =SUM(S12:S16) -> 25
A18: Residential mortgages | B18: 34764 | C18: 1236 | D18: 36000 | E18: 32817 | F18: 2390 | G18: 695 | H18: 98 | I18: 36000 | J18: 0
A19: Other personal | B19: 2940 | C19: 2926 | D19: 5866 | E19: 5339 | F19: 437 | G19: 90 | H19: 0 | I19: 5866 | J19: 0 | O19: =O10+O17 -> 30635
A20: Total Portfolio | B20: 66969 | C20: 16993 | D20: 83962 | E20: 72963 | F20: 8860 | G20: 2008 | H20: 131 | I20: 83962 | J20: 42
A23: ECL Allowance | B23: Loans ECL (€m) | C23: Off-Bal ECL (€m) | D23: Total ECL (€m) | E23: Stage 1 ECL (€m) | F23: Stage 2 ECL (€m) | G23: Stage 3 ECL (€m) | H23: POCI ECL (€m) | I23: Total Book ECL (€m) | L23: ECL Allowance | M23: Loans ECL (€m) | N23: Off-Bal ECL (€m) | O23: Total ECL (€m) | P23: Stage 1 ECL (€m) | Q23: Stage 2 ECL (€m) | R23: Stage 3 ECL (€m) | S23: POCI ECL (€m) | T23: Total Book ECL (€m)
A24: Non-property business: | L24: Non-Property Business(Corporate other)
A25: Natural resources | B25: 40 | C25: 3 | D25: 43 | E25: 17 | F25: 12 | G25: 14 | H25: 0 | I25: 43 | L25: Natural resources | M25: 40 | N25: 3 | O25: 43 | P25: 17 | Q25: 12 | R25: 14 | S25: 0 | T25: 43
A26: Of which renewables | B26: 17 | C26: 2 | D26: 19 | E26: 13 | F26: 6 | G26: 0 | H26: 0 | I26: 19 | L26: Manufacturing | M26: 58 | N26: 5 | O26: 63 | P26: 13 | Q26: 32 | R26: 18 | S26: 0
A27: Leisure | B27: 168 | C27: 3 | D27: 171 | E27: 19 | F27: 107 | G27: 46 | H27: -1 | I27: 171 | L27: Health, education and social work | M27: 83 | N27: 2 | O27: 85 | P27: 34 | Q27: 41 | R27: 12 | S27: -2
A28: Manufacturing | B28: 58 | C28: 5 | D28: 63 | E28: 13 | F28: 32 | G28: 18 | H28: 0 | I28: 63 | L28: Telecommunications, media and tech | M28: 22 | N28: 1 | O28: 23 | P28: 9 | Q28: 9 | R28: 5 | S28: 0
A29: Health, education and social work | B29: 83 | C29: 2 | D29: 85 | E29: 34 | F29: 41 | G29: 12 | H29: -2 | I29: 85 | L29: Financial, insurance and govt | M29: 20 | N29: 0 | O29: 20 | P29: 6 | Q29: 3 | R29: 11 | S29: 0
A30: Services | B30: 48 | C30: 4 | D30: 52 | E30: 16 | F30: 20 | G30: 16 | H30: 0 | I30: 52 | R30: =SUM(R25:R29) -> 60 | S30: =SUM(S25:S29) -> -2
A31: Agriculture, forestry and fishing | B31: 50 | C31: 3 | D31: 53 | E31: 7 | F31: 15 | G31: 36 | H31: -5 | I31: 53 | L31: Non-Property Business(SME)
A32: Retail and wholesale trade | B32: 55 | C32: 7 | D32: 62 | E32: 10 | F32: 31 | G32: 21 | H32: 0 | I32: 62 | L32: Leisure | M32: 168 | N32: 3 | O32: 171 | P32: 19 | Q32: 107 | R32: 46 | S32: -1 | T32: 171
A33: Transport and storage | B33: 29 | C33: 1 | D33: 30 | E33: 9 | F33: 10 | G33: 11 | H33: 0 | I33: 30 | L33: Services | M33: 48 | N33: 4 | O33: 52 | P33: 16 | Q33: 20 | R33: 16 | S33: 0
A34: Telecommunications, media and tech | B34: 22 | C34: 1 | D34: 23 | E34: 9 | F34: 9 | G34: 5 | H34: 0 | I34: 23 | L34: Agriculture, forestry and fishing | M34: 50 | N34: 3 | O34: 53 | P34: 7 | Q34: 15 | R34: 36 | S34: -5
A35: Financial, insurance and govt | B35: 20 | C35: 0 | D35: 20 | E35: 6 | F35: 3 | G35: 11 | H35: 0 | I35: 20 | L35: Retail and wholesale trade | M35: 55 | N35: 7 | O35: 62 | P35: 10 | Q35: 31 | R35: 21 | S35: 0
A36: Total non-property business | B36: 573 | C36: 29 | D36: 602 | E36: 140 | F36: 280 | G36: 190 | H36: -8 | I36: 602 | L36: Transport and storage | M36: 29 | N36: 1 | O36: 30 | P36: 9 | Q36: 10 | R36: 11 | S36: 0
A37: Property and construction | B37: 541 | C37: 23 | D37: 564 | E37: 87 | F37: 273 | G37: 205 | H37: -1 | I37: 564 | R37: =SUM(R32:R36) -> 130 | S37: =SUM(S32:S36) -> -6
A38: Residential mortgages | B38: 309 | C38: 1 | D38: 310 | E38: 19 | F38: 77 | G38: 207 | H38: 7 | I38: 310
A39: Other personal | B39: 97 | C39: 6 | D39: 103 | E39: 22 | F39: 36 | G39: 45 | H39: 0 | I39: 103
A40: Total Portfolio | B40: 1520 | C40: 59 | D40: 1579 | E40: 268 | F40: 666 | G40: 647 | H40: -2 | I40: 1579

Sheet 2022
A1: AIB Annual 2025
A2: Concentration by industry sector | B2: Loans (€m) | C2: Off-Bal (€m) | D2: Total Gross (€m) | E2: Stage 1 (€m) | F2: Stage 2 (€m) | G2: Stage 3 (€m) | H2: POCI (€m) | I2: Total Book (€m) | J2: Fin Guarantees (€m) | M2: Loans (€m) | N2: Off-Bal (€m) | O2: Total Gross (€m) | P2: Stage 1 (€m) | Q2: Stage 2 (€m) | R2: Stage 3 (€m) | S2: POCI (€m)
A3: Non-property business: | L3: Non-Property Business(Corporate other)
A4: Natural resources | B4: 2961 | C4: 1706 | D4: 4667 | E4: 4408 | F4: 225 | G4: 34 | H4: 0 | I4: 4667 | J4: 9 | L4: Natural resources | M4: 2961 | N4: 1706 | O4: 4667 | P4: 4408 | Q4: 225 | R4: 34 | S4: 0
A5: Of which renewables | B5: 2190 | C5: 802 | D5: 2992 | E5: 2786 | F5: 179 | G5: 27 | H5: 0 | I5: 2992 | J5: 0 | L5: Manufacturing | M5: 2849 | N5: 1929 | O5: 4778 | P5: 4297 | Q5: 396 | R5: 85 | S5: 0
A6: Leisure | B6: 2910 | C6: 604 | D6: 3514 | E6: 1422 | F6: 1713 | G6: 379 | H6: 0 | I6: 3514 | J6: 0 | L6: Health, education and social work | M6: 2012 | N6: 452 | O6: 2464 | P6: 2173 | Q6: 231 | R6: 60 | S6: 0
A7: Manufacturing | B7: 2849 | C7: 1929 | D7: 4778 | E7: 4297 | F7: 396 | G7: 85 | H7: 0 | I7: 4778 | J7: 0 | L7: Telecommunications, media and tech | M7: 1230 | N7: 369 | O7: 1599 | P7: 1503 | Q7: 71 | R7: 25 | S7: 0 | T7: 1599
A8: Health, education and social work | B8: 2012 | C8: 452 | D8: 2464 | E8: 2173 | F8: 231 | G8: 60 | H8: 0 | I8: 2464 | J8: 0 | L8: Financial, insurance and govt | M8: 502 | N8: 858 | O8: 1360 | P8: 1283 | Q8: 76 | R8: 1 | S8: 0 | T8: 1360
A9: Services | B9: 1832 | C9: 1045 | D9: 2877 | E9: 2544 | F9: 282 | G9: 51 | H9: 0 | I9: 2877 | J9: 0 | O9: =SUM(O4:O8) -> 14868 | R9: =SUM(R4:R8) -> 205 | S9: =SUM(S4:S8) -> 0
A10: Agriculture, forestry and fishing | B10: 1655 | C10: 669 | D10: 2324 | E10: 1975 | F10: 270 | G10: 79 | H10: 0 | I10: 2324 | J10: 0 | L10: Non-Property Business(SME)
A11: Retail and wholesale trade | B11: 1751 | C11: 1201 | D11: 2952 | E11: 2540 | F11: 318 | G11: 94 | H11: 0 | I11: 2952 | J11: 14 | L11: Leisure | M11: 2910 | N11: 604 | O11: 3514 | P11: 1422 | Q11: 1713 | R11: 379 | S11: 0
A12: Transport and storage | B12: 1661 | C12: 611 | D12: 2272 | E12: 1983 | F12: 271 | G12: 18 | H12: 0 | I12: 2272 | J12: 0 | L12: Services | M12: 1832 | N12: 1045 | O12: 2877 | P12: 2544 | Q12: 282 | R12: 51 | S12: 0
A13: Telecommunications, media and tech | B13: 1230 | C13: 369 | D13: 1599 | E13: 1503 | F13: 71 | G13: 25 | H13: 0 | I13: 1599 | J13: 0 | L13: Agriculture, forestry and fishing | M13: 1655 | N13: 669 | O13: 2324 | P13: 1975 | Q13: 270 | R13: 79 | S13: 0
A14: Financial, insurance and govt | B14: 502 | C14: 858 | D14: 1360 | E14: 1283 | F14: 76 | G14: 1 | H14: 0 | I14: 1360 | J14: 0 | L14: Retail and wholesale trade | M14: 1751 | N14: 1201 | O14: 2952 | P14: 2540 | Q14: 318 | R14: 94 | S14: 0
A15: Total non-property business | B15: 19363 | C15: 9444 | D15: 28807 | E15: 24128 | F15: 3853 | G15: 826 | H15: 0 | I15: 28807 | J15: 23 | L15: Transport and storage | M15: 1661 | N15: 611 | O15: 2272 | P15: 1983 | Q15: 271 | R15: 18 | S15: 0
A16: Property and construction | B16: 8617 | C16: 2384 | D16: 11001 | E16: 9056 | F16: 1509 | G16: 436 | H16: 0 | I16: 11001 | J16: 226 | O16: =SUM(O11:O15) -> 13939 | R16: =SUM(R11:R15) -> 621 | S16: =SUM(S11:S15) -> 0
A17: Residential mortgages | B17: 30279 | C17: 1168 | D17: 31447 | E17: 29553 | F17: 1161 | G17: 646 | H17: 87 | I17: 31447 | J17: 0
A18: Other personal | B18: 2723 | C18: 2866 | D18: 5589 | E18: 4810 | F18: 591 | G18: 188 | H18: 0 | I18: 5589 | J18: 0 | O18: =O9+O16 -> 28807
A19: Total Portfolio | B19: 60982 | C19: 15862 | D19: 76844 | E19: 67547 | F19: 7114 | G19: 2096 | H19: 87 | I19: 76844 | J19: 249
A23: ECL Allowance | B23: Loans ECL (€m) | C23: Off-Bal ECL (€m) | D23: Total ECL (€m) | E23: Stage 1 ECL (€m) | F23: Stage 2 ECL (€m) | G23: Stage 3 ECL (€m) | H23: POCI ECL (€m) | I23: Total Book ECL (€m) | L23: ECL Allowance | M23: Loans ECL (€m) | N23: Off-Bal ECL (€m) | O23: Total ECL (€m) | P23: Stage 1 ECL (€m) | Q23: Stage 2 ECL (€m) | R23: Stage 3 ECL (€m) | S23: POCI ECL (€m)
A24: Non-property business: | L24: Non-Property Business(Corporate other)
A25: Natural resources | B25: 59 | C25: 8 | D25: 67 | E25: 16 | F25: 26 | G25: 25 | H25: 0 | I25: 67 | L25: Natural resources | M25: 59 | N25: 8 | O25: 67 | P25: 16 | Q25: 26 | R25: 25 | S25: 0
A26: Of which renewables | B26: 49 | C26: 7 | D26: 56 | E26: 10 | F26: 24 | G26: 22 | H26: 0 | I26: 56 | L26: Manufacturing | M26: 88 | N26: 11 | O26: 99 | P26: 23 | Q26: 49 | R26: 27 | S26: 0
A27: Leisure | B27: 353 | C27: 12 | D27: 365 | E27: 21 | F27: 249 | G27: 95 | H27: 0 | I27: 365 | L27: Health, education and social work | M27: 51 | N27: 4 | O27: 55 | P27: 15 | Q27: 19 | R27: 21 | S27: 0
A28: Manufacturing | B28: 88 | C28: 11 | D28: 99 | E28: 23 | F28: 49 | G28: 27 | H28: 0 | I28: 99 | L28: Telecommunications, media and tech | M28: 24 | N28: 0 | O28: 24 | P28: 8 | Q28: 7 | R28: 9 | S28: 0
A29: Health, education and social work | B29: 51 | C29: 4 | D29: 55 | E29: 15 | F29: 19 | G29: 21 | H29: 0 | I29: 55 | L29: Financial, insurance and govt | M29: 31 | N29: 0 | O29: 31 | P29: 3 | Q29: 28 | R29: 0 | S29: 0
A30: Services | B30: 62 | C30: 4 | D30: 66 | E30: 12 | F30: 29 | G30: 25 | H30: 0 | I30: 66 | R30: =SUM(R25:R29) -> 82 | S30: =SUM(S25:S29) -> 0
A31: Agriculture, forestry and fishing | B31: 54 | C31: 3 | D31: 57 | E31: 11 | F31: 20 | G31: 26 | H31: 0 | I31: 57 | L31: Non-Property Business(SME)
A32: Retail and wholesale trade | B32: 76 | C32: 4 | D32: 80 | E32: 12 | F32: 33 | G32: 35 | H32: 0 | I32: 80 | L32: Leisure | M32: 353 | N32: 12 | O32: 365 | P32: 21 | Q32: 249 | R32: 95 | S32: 0
A33: Transport and storage | B33: 40 | C33: 1 | D33: 41 | E33: 7 | F33: 24 | G33: 10 | H33: 0 | I33: 41 | L33: Services | M33: 62 | N33: 4 | O33: 66 | P33: 12 | Q33: 29 | R33: 25 | S33: 0
A34: Telecommunications, media and tech | B34: 24 | C34: 0 | D34: 24 | E34: 8 | F34: 7 | G34: 9 | H34: 0 | I34: 24 | L34: Agriculture, forestry and fishing | M34: 54 | N34: 3 | O34: 57 | P34: 11 | Q34: 20 | R34: 26 | S34: 0
A35: Financial, insurance and govt | B35: 31 | C35: 0 | D35: 31 | E35: 3 | F35: 28 | G35: 0 | H35: 0 | I35: 31 | L35: Retail and wholesale trade | M35: 76 | N35: 4 | O35: 80 | P35: 12 | Q35: 33 | R35: 35 | S35: 0
A36: Total non-property business | B36: 838 | C36: 47 | D36: 885 | E36: 128 | F36: 484 | G36: 273 | H36: 0 | I36: 885 | L36: Transport and storage | M36: 40 | N36: 1 | O36: 41 | P36: 7 | Q36: 24 | R36: 10 | S36: 0
A37: Property and construction | B37: 320 | C37: 23 | D37: 343 | E37: 90 | F37: 121 | G37: 132 | H37: 0 | I37: 343 | R37: =SUM(R32:R36) -> 191 | S37: =SUM(S32:S36) -> 0
A38: Residential mortgages | B38: 283 | C38: 0 | D38: 283 | E38: 40 | F38: 37 | G38: 197 | H38: 9 | I38: 283
A39: Other personal | B39: 177 | C39: 8 | D39: 185 | E39: 26 | F39: 43 | G39: 116 | H39: 0 | I39: 185
A40: Total Portfolio | B40: 1618 | C40: 78 | D40: 1696 | E40: 284 | F40: 685 | G40: 718 | H40: 9 | I40: 1696

Sheet 2021
A1: AIB Annual 2025
A2: Concentration by industry sector | B2: Loans (€m) | C2: Off-Bal (€m) | D2: Total Gross (€m) | E2: Stage 1 (€m) | F2: Stage 2 (€m) | G2: Stage 3 (€m) | H2: POCI (€m) | I2: Total Book (€m) | J2: Fin Guarantees (€m) | N2: Loans (€m) | O2: Off-Bal (€m) | P2: Total Gross (€m) | Q2: Stage 1 (€m) | R2: Stage 2 (€m) | S2: Stage 3 (€m) | T2: POCI (€m)
A3: Non-property business: | M3: Non-Property Business(Corporate other)
A4: Agriculture | B4: 1677 | C4: 614 | D4: 2291 | E4: 1970 | F4: 223 | G4: 98 | H4: 0 | I4: 2291 | J4: 0 | M4: Energy | N4: 2214 | O4: 1100 | P4: 3314 | Q4: 3130 | R4: 146 | S4: 38 | T4: 0
A5: Energy | B5: 2214 | C5: 1100 | D5: 3314 | E5: 3130 | F5: 146 | G5: 38 | H5: 0 | I5: 3314 | J5: 0 | M5: Manufacturing | N5: 2542 | O5: 1733 | P5: 4275 | Q5: 3821 | R5: 387 | S5: 67 | T5: 0
A6: Manufacturing | B6: 2542 | C6: 1733 | D6: 4275 | E6: 3821 | F6: 387 | G6: 67 | H6: 0 | I6: 4275 | J6: 0 | M6: Financial | N6: 521 | O6: 504 | P6: 1025 | Q6: 957 | R6: 65 | S6: 3 | T6: 0
A7: Distribution | B7: 4685 | C7: 1308 | D7: 5993 | E7: 2880 | F7: 2404 | G7: 709 | H7: 0 | I7: 5993 | J7: 0 | P7: =SUM(P4:P6) -> 8614 | S7: =SUM(S4:S6) -> 108 | T7: =SUM(T4:T6) -> 0
A8: Transport | B8: 2209 | C8: 632 | D8: 2841 | E8: 2448 | F8: 347 | G8: 46 | H8: 0 | I8: 2841 | J8: 0 | M8: Non-Property Business(SME)
A9: Financial | B9: 521 | C9: 504 | D9: 1025 | E9: 957 | F9: 65 | G9: 3 | H9: 0 | I9: 1025 | J9: 0 | M9: Agriculture | N9: 1677 | O9: 614 | P9: 2291 | Q9: 1970 | R9: 223 | S9: 98 | T9: 0
A10: Other services | B10: 4831 | C10: 2189 | D10: 7020 | E10: 6108 | F10: 686 | G10: 226 | H10: 0 | I10: 7020 | J10: 0 | M10: Distribution | N10: 4685 | O10: 1308 | P10: 5993 | Q10: 2880 | R10: 2404 | S10: 709 | T10: 0
A11: Property and construction | B11: 7360 | C11: 2365 | D11: 9725 | E11: 7571 | F11: 1483 | G11: 671 | H11: 0 | I11: 9725 | J11: 243 | M11: Transport | N11: 2209 | O11: 632 | P11: 2841 | Q11: 2448 | R11: 347 | S11: 46 | T11: 0
A12: Residential mortgages | B12: 29407 | C12: 1245 | D12: 30652 | E12: 28167 | F12: 1452 | G12: 930 | H12: 103 | I12: 30652 | J12: 0 | M12: Other services | N12: 4831 | O12: 2189 | P12: 7020 | Q12: 6108 | R12: 686 | S12: 226 | T12: 0
A13: Other personal | B13: 2704 | C13: 2856 | D13: 5560 | E13: 4909 | F13: 393 | G13: 258 | H13: 0 | I13: 5560 | J13: 0 | P13: =SUM(P9:P12) -> 18145 | S13: =SUM(S9:S12) -> 1079 | T13: =SUM(T9:T12) -> 0
A14: Total Portfolio | B14: 58150 | C14: 14546 | D14: 72696 | E14: 61961 | F14: 7586 | G14: 3046 | H14: 103 | I14: 72696 | J14: 243
A17: ECL Allowance | B17: Loans ECL (€m) | C17: Off-Bal ECL (€m) | D17: Total ECL (€m) | E17: Stage 1 ECL (€m) | F17: Stage 2 ECL (€m) | G17: Stage 3 ECL (€m) | H17: POCI ECL (€m) | I17: Total Book ECL (€m) | M17: ECL Allowance | N17: Loans ECL (€m) | O17: Off-Bal ECL (€m) | P17: Total ECL (€m) | Q17: Stage 1 ECL (€m) | R17: Stage 2 ECL (€m) | S17: Stage 3 ECL (€m) | T17: POCI ECL (€m) | U17: Total Book ECL (€m)
A18: Non-property business: | M18: Non-Property Business(Corporate other)
A19: Agriculture | B19: 59 | C19: 4 | D19: 63 | E19: 10 | F19: 15 | G19: 38 | H19: 0 | I19: 63 | M19: Energy | N19: 32 | O19: 1 | P19: 33 | Q19: 13 | R19: 18 | S19: 2 | T19: 0
A20: Energy | B20: 32 | C20: 1 | D20: 33 | E20: 13 | F20: 18 | G20: 2 | H20: 0 | I20: 33 | M20: Manufacturing | N20: 53 | O20: 9 | P20: 62 | Q20: 17 | R20: 27 | S20: 18 | T20: 0
A21: Manufacturing | B21: 53 | C21: 9 | D21: 62 | E21: 17 | F21: 27 | G21: 18 | H21: 0 | I21: 62 | M21: Financial | N21: 25 | O21: 2 | P21: 27 | Q21: 5 | R21: 20 | S21: 2 | T21: 0
A22: Distribution | B22: 557 | C22: 20 | D22: 577 | E22: 40 | F22: 388 | G22: 149 | H22: 0 | I22: 577 | S22: =SUM(S19:S21) -> 22 | T22: =SUM(T19:T21) -> 0
A23: Transport | B23: 67 | C23: 3 | D23: 70 | E23: 11 | F23: 34 | G23: 25 | H23: 0 | I23: 70 | M23: Non-Property Business(SME)
A24: Financial | B24: 25 | C24: 2 | D24: 27 | E24: 5 | F24: 20 | G24: 2 | H24: 0 | I24: 27 | M24: Agriculture | N24: 59 | O24: 4 | P24: 63 | Q24: 10 | R24: 15 | S24: 38 | T24: 0
A25: Other services | B25: 175 | C25: 13 | D25: 188 | E25: 41 | F25: 62 | G25: 85 | H25: 0 | I25: 188 | M25: Distribution | N25: 557 | O25: 20 | P25: 577 | Q25: 40 | R25: 388 | S25: 149 | T25: 0
A26: Property and construction | B26: 313 | C26: 20 | D26: 333 | E26: 53 | F26: 93 | G26: 187 | H26: 0 | I26: 333 | M26: Transport | N26: 67 | O26: 3 | P26: 70 | Q26: 11 | R26: 34 | S26: 25 | T26: 0
A27: Residential mortgages | B27: 382 | C27: 0 | D27: 382 | E27: 35 | F27: 41 | G27: 275 | H27: 31 | I27: 382 | M27: Other services | N27: 175 | O27: 13 | P27: 188 | Q27: 41 | R27: 62 | S27: 85 | T27: 0
A28: Other personal | B28: 222 | C28: 7 | D28: 229 | E28: 32 | F28: 38 | G28: 159 | H28: 0 | I28: 229 | S28: =SUM(S24:S27) -> 297 | T28: =SUM(T24:T27) -> 0
A29: Total Portfolio | B29: 1885 | C29: 79 | D29: 1964 | E29: 257 | F29: 736 | G29: 940 | H29: 31 | I29: 1964

Sheet 2020
A1: AIB Annual 2025
A2: Concentration by industry sector | B2: Loans (€m) | C2: Off-Bal (€m) | D2: Total Gross (€m) | E2: Stage 1 (€m) | F2: Stage 2 (€m) | G2: Stage 3 (€m) | H2: POCI (€m) | I2: Total Book (€m) | J2: Fin Guarantees (€m) | M2: Loans (€m) | N2: Off-Bal (€m) | O2: Total Gross (€m) | P2: Stage 1 (€m) | Q2: Stage 2 (€m) | R2: Stage 3 (€m) | S2: POCI (€m)
A3: Non-property business: | L3: Non-Property Business(Corporate other)
A4: Agriculture | B4: 1671 | C4: 607 | D4: 2278 | E4: 1740 | F4: 439 | G4: 99 | H4: 0 | I4: 2278 | J4: 0 | L4: Energy | M4: 1815 | N4: 919 | O4: 2734 | P4: 2607 | Q4: 91 | R4: 36 | S4: 0
A5: Energy | B5: 1815 | C5: 919 | D5: 2734 | E5: 2607 | F5: 91 | G5: 36 | H5: 0 | I5: 2734 | J5: 0 | L5: Manufacturing | M5: 2547 | N5: 1593 | O5: 4140 | P5: 3346 | Q5: 707 | R5: 87 | S5: 0
A6: Manufacturing | B6: 2547 | C6: 1593 | D6: 4140 | E6: 3346 | F6: 707 | G6: 87 | H6: 0 | I6: 4140 | J6: 0 | L6: Financial | M6: 526 | N6: 570 | O6: 1096 | P6: 991 | Q6: 96 | R6: 9 | S6: 0
A7: Distribution | B7: 4986 | C7: 1271 | D7: 6257 | E7: 2773 | F7: 2911 | G7: 573 | H7: 0 | I7: 6257 | J7: 0 | O7: =SUM(O4:O6) -> 7970 | R7: =SUM(R4:R6) -> 132 | S7: =SUM(S4:S6) -> 0
A8: Transport | B8: 1829 | C8: 506 | D8: 2335 | E8: 1810 | F8: 452 | G8: 73 | H8: 0 | I8: 2335 | J8: 0 | L8: Non-Property Business(SME)
A9: Financial | B9: 526 | C9: 570 | D9: 1096 | E9: 991 | F9: 96 | G9: 9 | H9: 0 | I9: 1096 | J9: 0 | L9: Agriculture | M9: 1671 | N9: 607 | O9: 2278 | P9: 1740 | Q9: 439 | R9: 99 | S9: 0
A10: Other services | B10: 5227 | C10: 2114 | D10: 7341 | E10: 5977 | F10: 1139 | G10: 225 | H10: 0 | I10: 7341 | J10: 0 | L10: Distribution | M10: 4986 | N10: 1271 | O10: 6257 | P10: 2773 | Q10: 2911 | R10: 573 | S10: 0
A11: Property and construction | B11: 7260 | C11: 1940 | D11: 9200 | E11: 5977 | F11: 2321 | G11: 902 | H11: 0 | I11: 9200 | J11: 75 | L11: Transport | M11: 1829 | N11: 506 | O11: 2335 | P11: 1810 | Q11: 452 | R11: 73 | S11: 0
A12: Residential mortgages | B12: 30649 | C12: 837 | D12: 31486 | E12: 27354 | F12: 1956 | G12: 1992 | H12: 184 | I12: 31486 | J12: 0 | L12: Other services | M12: 5227 | N12: 2114 | O12: 7341 | P12: 5977 | Q12: 1139 | R12: 225 | S12: 0
A13: Other personal | B13: 2766 | C13: 2869 | D13: 5635 | E13: 4837 | F13: 556 | G13: 242 | H13: 0 | I13: 5635 | J13: 0 | O13: =SUM(O9:O12) -> 18211 | R13: =SUM(R9:R12) -> 970 | S13: =SUM(S9:S12) -> 0
A14: Total Portfolio | B14: 59276 | C14: 13226 | D14: 72502 | E14: 57412 | F14: 10668 | G14: 4238 | H14: 184 | I14: 72502 | J14: 75
A18: ECL Allowance | B18: Loans ECL (€m) | C18: Off-Bal ECL (€m) | D18: Total ECL (€m) | E18: Stage 1 ECL (€m) | F18: Stage 2 ECL (€m) | G18: Stage 3 ECL (€m) | H18: POCI ECL (€m) | I18: Total Book ECL (€m) | L18: ECL Allowance | M18: Loans ECL (€m) | N18: Off-Bal ECL (€m) | O18: Total ECL (€m) | P18: Stage 1 ECL (€m) | Q18: Stage 2 ECL (€m) | R18: Stage 3 ECL (€m) | S18: POCI ECL (€m) | T18: Total Book ECL (€m)
A19: Non-property business: | L19: Non-Property Business(Corporate other)
A20: Agriculture | B20: 66 | C20: 4 | D20: 70 | E20: 15 | F20: 23 | G20: 32 | H20: 0 | I20: 70 | L20: Energy | M20: 15 | N20: 2 | O20: 17 | P20: 12 | Q20: 3 | R20: 2 | S20: 0
A21: Energy | B21: 15 | C21: 2 | D21: 17 | E21: 12 | F21: 3 | G21: 2 | H21: 0 | I21: 17 | L21: Manufacturing | M21: 84 | N21: 8 | O21: 92 | P21: 15 | Q21: 50 | R21: 27 | S21: 0
A22: Manufacturing | B22: 84 | C22: 8 | D22: 92 | E22: 15 | F22: 50 | G22: 27 | H22: 0 | I22: 92 | L22: Financial | M22: 22 | N22: 1 | O22: 23 | P22: 4 | Q22: 15 | R22: 4 | S22: 0
A23: Distribution | B23: 590 | C23: 17 | D23: 607 | E23: 42 | F23: 412 | G23: 153 | H23: 0 | I23: 607 | O23: =SUM(O20:O22) -> 132 | R23: =SUM(R20:R22) -> 33 | S23: =SUM(S20:S22) -> 0
A24: Transport | B24: 63 | C24: 2 | D24: 65 | E24: 10 | F24: 20 | G24: 35 | H24: 0 | I24: 65 | L24: Non-Property Business(SME)
A25: Financial | B25: 22 | C25: 1 | D25: 23 | E25: 4 | F25: 15 | G25: 4 | H25: 0 | I25: 23 | L25: Agriculture | M25: 66 | N25: 4 | O25: 70 | P25: 15 | Q25: 23 | R25: 32 | S25: 0
A26: Other services | B26: 197 | C26: 12 | D26: 209 | E26: 43 | F26: 92 | G26: 74 | H26: 0 | I26: 209 | L26: Distribution | M26: 590 | N26: 17 | O26: 607 | P26: 42 | Q26: 412 | R26: 153 | S26: 0
A27: Property and construction | B27: 396 | C27: 30 | D27: 426 | E27: 82 | F27: 140 | G27: 204 | H27: 0 | I27: 426 | L27: Transport | M27: 63 | N27: 2 | O27: 65 | P27: 10 | Q27: 20 | R27: 35 | S27: 0
A28: Residential mortgages | B28: 843 | C28: 0 | D28: 843 | E28: 39 | F28: 73 | G28: 662 | H28: 69 | I28: 843 | L28: Other services | M28: 197 | N28: 12 | O28: 209 | P28: 43 | Q28: 92 | R28: 74 | S28: 0
A29: Other personal | B29: 234 | C29: 7 | D29: 241 | E29: 42 | F29: 56 | G29: 143 | H29: 0 | I29: 241 | O29: =SUM(O25:O28) -> 951 | R29: =SUM(R25:R28) -> 294 | S29: =SUM(S25:S28) -> 0
A30: Total Portfolio | B30: 2510 | C30: 83 | D30: 2593 | E30: 304 | F30: 884 | G30: 1336 | H30: 69 | I30: 2593

Sheet Macro Forcast(5y)
B1: AIB Annual 2025
D2: Base | I2: Downside 1(Escalating geopolitical tensions) | R2: ECL allowance at 31 December 2025
B4: Geography / Macroeconomic factor (%) | C4: Estimate: 2025 | D4: Base: 2026 | E4: Base: 2027 | F4: Base: 2028 | G4: Base: 2029 | H4: Base: 2030 | I4: Downside 1: 2026 | J4: Downside 1: 2027 | K4: Downside 1: 2028 | L4: Downside 1: 2029 | M4: Downside 1: 2030 | O4: Asset Class / Portfolio Segment | P4: Reported | Q4: 100% Base(2026) | R4: 100% Downside 1 (Escalating Tensions) | S4: 100% Downside 2 (Trade War/FDI Shock) | T4: 100% Upside (Easing Tensions)
B5: Republic of Ireland | O5: Loans and advances to customers:
B6: GDP growth | C6: 7 | D6: 3 | E6: 3.8 | F6: 2.8 | G6: 2.8 | H6: 2.7 | I6: 1.7 | J6: 1.3 | K6: 2.7 | L6: 3.1 | M6: 3.3 | O6: Residential mortgages | P6: 176 | Q6: 150 | R6: 204 | S6: 427 | T6: 135
B7: Residential property price growth | C7: 3.5 | D7: 2.5 | E7: 2 | F7: 2 | G7: 2 | H7: 2 | I7: -6 | J7: -2.5 | K7: 4 | L7: 2.5 | M7: 2.5 | O7: Other personal | P7: 131 | Q7: 122 | R7: 139 | S7: 168 | T7: 117
B8: Unemployment rate | C8: 4.8 | D8: 5 | E8: 5.2 | F8: 5.1 | G8: 5 | H8: 4.9 | I8: 5.9 | J8: 8 | K8: 10 | L8: 9.1 | M8: 8.4 | O8: Property and construction | P8: 432 | Q8: 395 | R8: 487 | S8: 586 | T8: 357
B9: Commercial property price growth | C9: 1 | D9: 5 | E9: 3 | F9: 3 | G9: 3 | H9: 3 | I9: -10 | J9: -3.5 | K9: 3 | L9: 3 | M9: 2 | O9: Non-property business | P9: 404 | Q9: 339 | R9: 480 | S9: 700 | T9: 313
B10: Employment growth | C10: 2.2 | D10: 1.8 | E10: 1.6 | F10: 1.9 | G10: 2 | H10: 1.9 | I10: 0.6 | J10: -1 | K10: 0.6 | L10: 2.5 | M10: 2 | O10: Total Loans and Advances | P10: 1143 | Q10: 1006 | R10: 1310 | S10: 1881 | T10: 922
B11: Average disposable income growth | C11: 5.7 | D11: 4.6 | E11: 4 | F11: 5.5 | G11: 5.5 | H11: 5.5 | I11: 3.8 | J11: 1.7 | K11: 2.7 | L11: 4.7 | M11: 5 | O11: Off-balance sheet loan commitments | P11: 38 | Q11: 34 | R11: 41 | S11: 53 | T11: 32
B12: Inflation | C12: 1.7 | D12: 1.9 | E12: 2.1 | F12: 2 | G12: 2 | H12: 2 | I12: 1.8 | J12: 1.7 | K12: 2 | L12: 2 | M12: 2 | O12: Financial guarantee contracts | P12: 10 | Q12: 9 | R12: 10 | S12: 11 | T12: 8
O13: Total ECL Portfolio Allowance | P13: 1191 | Q13: 1049 | R13: 1361 | S13: 1945 | T13: 962
O14: Of which: AIB UK segment | P14: 94 | Q14: 83 | R14: 109 | S14: 114 | T14: 78
C15: Downside 2 (Global trade war/Irish FDI shock) | H15: Upside (Easing geopolitical tensions)
B17: Geography / Macroeconomic factor (%) | C17: Downside 2: 2026 | D17: Downside 2: 2027 | E17: Downside 2: 2028 | F17: Downside 2: 2029 | G17: Downside 2: 2030 | H17: Upside: 2026 | I17: Upside: 2027 | J17: Upside: 2028 | K17: Upside: 2029 | L17: Upside: 2030 | O17: Reported ECL=Weighted average of all scenarios+management overlays+expert judgement
B18: Republic of Ireland
B19: GDP growth | C19: -0.5 | D19: -4.3 | E19: 2.4 | F19: 3.3 | G19: 3.8 | H19: 5.9 | I19: 5.4 | J19: 3.4 | K19: 1.9 | L19: 2.4
B20: Residential property price growth | C20: -10 | D20: -12.5 | E20: -0.5 | F20: 1 | G20: 1.5 | H20: 6.5 | I20: 5 | J20: 4 | K20: 3 | L20: 2.5
B21: Unemployment rate | C21: 6.7 | D21: 9.7 | E21: 12.1 | F21: 12.5 | G21: 12.6 | H21: 4.5 | I21: 4.4 | J21: 4.3 | K21: 4.3 | L21: 4.3
B22: Commercial property price growth | C22: -11.5 | D22: -13 | E22: -1 | F22: 2.5 | G22: 3.5 | H22: 7 | I22: 10 | J22: 5 | K22: 4 | L22: 3
B23: Employment growth | C23: -1.1 | D23: -2.8 | E23: -1.6 | F23: 1.3 | G23: 1.8 | H23: 2.7 | I23: 2.5 | J23: 2.1 | K23: 1.9 | L23: 1.8
B24: Average disposable income growth | C24: 2.3 | D24: 0.1 | E24: 1.4 | F24: 4.3 | G24: 5 | H24: 7.1 | I24: 7.6 | J24: 6.5 | K24: 5.1 | L24: 5
B25: Inflation | C25: 1.8 | D25: 1.2 | E25: 1.6 | F25: 2 | G25: 2 | H25: 3.4 | I25: 4.6 | J25: 3 | K25: 2.5 | L25: 2
B28: Scenario Probability Weighting (%) | C28: 45992 | D28: 45627
B29: Base | C29: 0.5 | D29: 0.5
B30: Downside 1 (Geopolitical tensions / Escalating tensions) | C30: 0.4 | D30: 0.4
B31: Downside 2 (Global trade war/Irish FDI shock vs. Credit crunch) | C31: 0.05 | D31: 0.05
B32: Upside (Easing tensions / Quick recovery) | C32: 0.05 | D32: 0.05

Sheet Macro(5y Avg)
B1: AIB Annual 2025
C2: December 2025 5 year (2026-2030) average forecast | G2: December 2024 5 year (2025-2029) average forecast
B5: Geography / Macroeconomic factor (%) | C5: Dec 2025: Base | D5: Dec 2025: Downside 1 | E5: Dec 2025: Downside 2 | F5: Dec 2025: Upside | G5: Dec 2024: Base | H5: Dec 2024: Downside 1 | I5: Dec 2024: Downside 2 | J5: Dec 2024: Upside
B6: Republic of Ireland
B7: GDP growth | C7: 3 | D7: 2.4 | E7: 0.9 | F7: 3.8 | G7: 3 | H7: 1.8 | I7: 0.7 | J7: 3.8
B8: Residential property price growth | C8: 2.1 | D8: 0.1 | E8: -4.1 | F8: 4.2 | G8: 2.5 | H8: -0.1 | I8: -4.7 | J8: 4.2
B9: Unemployment rate | C9: 5 | D9: 7.3 | E9: 8.7 | F9: 4.4 | G9: 4.5 | H9: 7.4 | I9: 10.1 | J9: 3.9
B10: Commercial property price growth | C10: 3.4 | D10: -1.1 | E10: -3.9 | F10: 5.8 | G10: 3.4 | H10: -1.2 | I10: -5.2 | J10: 5.8
B11: Employment growth | C11: 1.8 | D11: 0.9 | E11: -0.5 | F11: 2.2 | G11: 1.5 | H11: 1 | I11: -0.6 | J11: 1.9
B12: Average disposable income growth | C12: 5 | D12: 3.6 | E12: 2.6 | F12: 6.3 | G12: 4.4 | H12: 4 | I12: 3 | J12: 6.5
B13: Inflation | C13: 2 | D13: 1.9 | E13: 1.7 | F13: 3.1 | G13: 2 | H13: 2.9 | I13: 1.9 | J13: 3.1
B15: Return on Shareholder Equity (RoE) and Return on Tangible Equity
B16: (RoTE)
B17: Metric Component | C17: 2025 (€ m) | D17: 2024 (€ m)
B18: Profit after tax | C18: 2139 | D18: 2351
B19: AT1 coupons paid | C19: -85 | D19: -80
B20: Attributable earnings | C20: 2054 | D20: 2271
B21: Average Shareholder Equity | C21: 13792 | D21: 14078
B22: Return on Shareholder Equity (RoE) | C22: 0.149 | D22: 0.161
B24: Average RWA | C24: 58693 | D24: 60747
B25: RWA * 14% CET1 target | C25: 8217 | D25: 8505
B26: Return on Tangible Equity (RoTE) | C26: 0.25 | D26: 0.267
B30: CET1 Ratio | C30: 0.162 | D30: 0.151
B33: Regulatory Capital Requirements | C33: 31 Dec 2025 (%)
B34: CET1 Requirements
B35: Pillar 1 | C35: 0.045
B36: Pillar 2 requirement (P2R) | C36: 0.0135
B37: Capital Conservation Buffer (CCB) | C37: 0.025
B38: Other Systemically Important Institutions Buffer (O-SII) | C38: 0.015
B39: Countercyclical buffer (CCyB) Impact | C39: 0.0144
B40: CET1 Requirement | C40: 0.1129
B41: AT1 | C41: 0.0195
B42: Tier 2 | C42: 0.026
B43: Total Capital Requirement | C43: 0.1584
B46: year | C46: Modified GNI at constant Market
B47: 2019 | C47: 240674
B48: 2020 | C48: 234772
B49: =B48+1 -> 2021 | C49: 267083
B50: =B49+1 -> 2022 | C50: 275832
B51: =B50+1 -> 2023 | C51: 291428
B52: =B51+1 -> 2024 | C52: 305374
B53: =B52+1 -> 2025 | C53: =C52*1.024 -> 312702.98 | D53: Real GNP grew by (2.4\%) in 2025.
